{
  "PluginsIndex": {
    "description": [],
    "enableJsonFlag": [],
    "examples": [],
    "flags": [],
    "plugins": [],
    "run": [],
    "createTree": [
      "plugin"
    ],
    "display": [
      "plugins"
    ],
    "displayJitPlugins": [
      "jitPlugins"
    ],
    "formatPlugin": [
      "plugin"
    ]
  },
  "PluginsInspect": {
    "args": [],
    "description": [],
    "enableJsonFlag": [],
    "examples": [],
    "flags": [],
    "strict": [],
    "usage": [],
    "plugins": [],
    "findDep": [
      "plugin",
      "dependency"
    ],
    "findPlugin": [
      "pluginName"
    ],
    "inspect": [
      "pluginName",
      "param"
    ],
    "run": []
  },
  "trimUntil": [
    "fsPath",
    "part"
  ],
  "PluginsInstall": {
    "aliases": [],
    "args": [],
    "description": [],
    "enableJsonFlag": [],
    "examples": [],
    "flags": [],
    "strict": [],
    "summary": [],
    "parsePlugin": [
      "plugins",
      "input"
    ],
    "run": []
  },
  "getNameAndTag": [
    "input"
  ],
  "validateNpmPkgName": [
    "name"
  ],
  "PluginsLink": {
    "args": [],
    "description": [],
    "examples": [],
    "flags": [],
    "summary": [],
    "run": []
  },
  "Reset": {
    "flags": [],
    "summary": [],
    "run": []
  },
  "PluginsUninstall": {
    "aliases": [],
    "args": [],
    "description": [],
    "examples": [],
    "flags": [],
    "strict": [],
    "run": []
  },
  "removeTags": [
    "plugin"
  ],
  "PluginsUpdate": {
    "description": [],
    "flags": [],
    "run": []
  },
  "update": [],
  "determineLogLevel": [
    "config",
    "flags",
    "defaultLevel"
  ],
  "NPM": {
    "bin": [],
    "config": [],
    "logLevel": [],
    "constructor": [
      "param"
    ],
    "exec": [
      "param",
      "options"
    ],
    "install": [
      "args",
      "opts"
    ],
    "uninstall": [
      "args",
      "opts"
    ],
    "update": [
      "args",
      "opts"
    ],
    "view": [
      "args",
      "opts"
    ],
    "findNpm": []
  },
  "Plugins": {
    "config": [],
    "npm": [],
    "debug": [],
    "logLevel": [],
    "constructor": [
      "options"
    ],
    "pjsonPath": [],
    "add": [
      "param"
    ],
    "friendlyName": [
      "name"
    ],
    "hasPlugin": [
      "name"
    ],
    "install": [
      "name",
      "param"
    ],
    "link": [
      "p",
      "param"
    ],
    "list": [],
    "maybeUnfriendlyName": [
      "name"
    ],
    "pjson": [],
    "remove": [
      "name"
    ],
    "unfriendlyName": [
      "name"
    ],
    "uninstall": [
      "name"
    ],
    "update": [],
    "ensurePJSON": [],
    "isValidPlugin": [
      "p"
    ],
    "maybeCleanUp": [],
    "npmHasPackage": [
      "name",
      "param"
    ],
    "readPJSON": [],
    "savePJSON": [
      "pjson"
    ]
  },
  "fileExists": [
    "filePath"
  ],
  "dedupePlugins": [
    "plugins"
  ],
  "extractIssuesLocation": [
    "bugs",
    "repository"
  ],
  "notifyUser": [
    "plugin",
    "output"
  ],
  "normalizePlugins": [
    "input"
  ],
  "spawn": [
    "modulePath",
    "param",
    "param"
  ],
  "shouldPrint": [
    "str"
  ],
  "compare": [
    "a",
    "b"
  ],
  "sortBy": [
    "arr",
    "fn"
  ],
  "uniq": [
    "arr"
  ],
  "uniqWith": [
    "arr",
    "fn"
  ],
  "Yarn": {
    "bin": [],
    "config": [],
    "logLevel": [],
    "constructor": [
      "param"
    ],
    "exec": [
      "param",
      "options"
    ],
    "install": [
      "args",
      "opts"
    ],
    "findYarn": []
  }
}