{
  "Browser": {
    "constructor": [],
    "process": [],
    "createBrowserContext": [
      "options"
    ],
    "browserContexts": [],
    "defaultBrowserContext": [],
    "wsEndpoint": [],
    "newPage": [
      "options"
    ],
    "getWindowBounds": [
      "windowId"
    ],
    "setWindowBounds": [
      "windowId",
      "windowBounds"
    ],
    "targets": [],
    "target": [],
    "waitForTarget": [
      "predicate",
      "param"
    ],
    "pages": [
      "param"
    ],
    "version": [],
    "userAgent": [],
    "close": [],
    "disconnect": [],
    "cookies": [],
    "setCookie": [
      "param"
    ],
    "deleteCookie": [
      "param"
    ],
    "deleteMatchingCookies": [
      "param"
    ],
    "setPermission": [
      "origin",
      "param"
    ],
    "installExtension": [
      "path"
    ],
    "uninstallExtension": [
      "id"
    ],
    "screens": [],
    "addScreen": [
      "params"
    ],
    "removeScreen": [
      "screenId"
    ],
    "isConnected": [],
    "connected": [],
    "disposeSymbol": [],
    "asyncDisposeSymbol": [],
    "protocol": [],
    "debugInfo": [],
    "isNetworkEnabled": []
  },
  "BrowserContext": {
    "constructor": [],
    "targets": [],
    "startScreenshot": [],
    "waitForScreenshotOperations": [],
    "waitForTarget": [
      "predicate",
      "param"
    ],
    "pages": [
      "includeAll"
    ],
    "overridePermissions": [
      "origin",
      "permissions"
    ],
    "setPermission": [
      "origin",
      "param"
    ],
    "clearPermissionOverrides": [],
    "newPage": [
      "options"
    ],
    "browser": [],
    "close": [],
    "cookies": [],
    "setCookie": [
      "param"
    ],
    "deleteCookie": [
      "param"
    ],
    "deleteMatchingCookies": [
      "param"
    ],
    "closed": [],
    "id": [],
    "disposeSymbol": [],
    "asyncDisposeSymbol": []
  },
  "CDPSession": {
    "constructor": [],
    "connection": [],
    "detached": [],
    "parentSession": [],
    "send": [
      "method",
      "params",
      "options"
    ],
    "detach": [],
    "id": []
  },
  "DeviceRequestPrompt": {
    "devices": [],
    "waitForDevice": [
      "filter",
      "options"
    ],
    "select": [
      "device"
    ],
    "cancel": []
  },
  "Dialog": {
    "handled": [],
    "constructor": [
      "type",
      "message",
      "param"
    ],
    "type": [],
    "message": [],
    "defaultValue": [],
    "handle": [
      "options"
    ],
    "accept": [
      "promptText"
    ],
    "dismiss": []
  },
  "ElementHandle": {
    "frame": [],
    "$": [
      "selector"
    ],
    "$$": [
      "selector",
      "options"
    ],
    "$eval": [
      "selector",
      "pageFunction",
      "param"
    ],
    "$$eval": [
      "selector",
      "pageFunction",
      "param"
    ],
    "waitForSelector": [
      "selector",
      "options"
    ],
    "isVisible": [],
    "isHidden": [],
    "toElement": [
      "tagName"
    ],
    "contentFrame": [],
    "clickablePoint": [
      "offset"
    ],
    "hover": [
      "this"
    ],
    "click": [
      "this",
      "options"
    ],
    "drag": [
      "this",
      "target"
    ],
    "dragEnter": [
      "this",
      "data"
    ],
    "dragOver": [
      "this",
      "data"
    ],
    "drop": [
      "this",
      "data"
    ],
    "dragAndDrop": [
      "this",
      "target",
      "options"
    ],
    "select": [
      "param"
    ],
    "uploadFile": [
      "this",
      "param"
    ],
    "tap": [
      "this"
    ],
    "touchStart": [
      "this"
    ],
    "touchMove": [
      "this",
      "touch"
    ],
    "touchEnd": [
      "this"
    ],
    "focus": [],
    "type": [
      "text",
      "options"
    ],
    "press": [
      "key",
      "options"
    ],
    "boundingBox": [],
    "boxModel": [],
    "screenshot": [
      "options"
    ],
    "isIntersectingViewport": [
      "this",
      "options"
    ],
    "scrollIntoView": [
      "this"
    ],
    "asLocator": [
      "this"
    ],
    "autofill": [
      "data"
    ],
    "backendNodeId": []
  },
  "accept": [
    "f"
  ],
  "fail": [
    "e"
  ],
  "next": [],
  "bindIsolatedHandle": [
    "target",
    "_"
  ],
  "transformQuadWithOffsets": [
    "quad",
    "offsets"
  ],
  "intersectBoundingBox": [
    "box",
    "width",
    "height"
  ],
  "Frame": {
    "page": [],
    "goto": [
      "url",
      "options"
    ],
    "waitForNavigation": [
      "options"
    ],
    "frameElement": [],
    "evaluateHandle": [
      "pageFunction",
      "param"
    ],
    "evaluate": [
      "pageFunction",
      "param"
    ],
    "locator": [
      "func"
    ],
    "$": [
      "selector"
    ],
    "$$": [
      "selector",
      "options"
    ],
    "$eval": [
      "selector",
      "pageFunction",
      "param"
    ],
    "$$eval": [
      "selector",
      "pageFunction",
      "param"
    ],
    "waitForSelector": [
      "selector",
      "options"
    ],
    "waitForFunction": [
      "pageFunction",
      "options",
      "param"
    ],
    "content": [],
    "setContent": [
      "html",
      "options"
    ],
    "name": [],
    "url": [],
    "parentFrame": [],
    "childFrames": [],
    "detached": [],
    "isDetached": [],
    "addScriptTag": [
      "options"
    ],
    "addStyleTag": [
      "options"
    ],
    "click": [
      "selector",
      "options"
    ],
    "focus": [
      "selector"
    ],
    "hover": [
      "selector"
    ],
    "select": [
      "selector",
      "param"
    ],
    "tap": [
      "selector"
    ],
    "type": [
      "selector",
      "text",
      "options"
    ],
    "title": []
  },
  "HTTPRequest": {
    "id": [],
    "_interceptionId": [],
    "_failureText": [],
    "_response": [],
    "_fromMemoryCache": [],
    "_redirectChain": [],
    "interception": [],
    "client": [],
    "constructor": [],
    "url": [],
    "continueRequestOverrides": [],
    "responseForRequest": [],
    "abortErrorReason": [],
    "interceptResolutionState": [],
    "isInterceptResolutionHandled": [],
    "enqueueInterceptAction": [
      "pendingHandler"
    ],
    "_abort": [
      "errorReason"
    ],
    "_respond": [
      "response"
    ],
    "_continue": [
      "overrides"
    ],
    "finalizeInterceptions": [],
    "resourceType": [],
    "method": [],
    "postData": [],
    "hasPostData": [],
    "fetchPostData": [],
    "headers": [],
    "response": [],
    "frame": [],
    "isNavigationRequest": [],
    "initiator": [],
    "redirectChain": [],
    "failure": [],
    "verifyInterception": [],
    "canBeIntercepted": [],
    "continue": [
      "param",
      "priority"
    ],
    "respond": [
      "response",
      "priority"
    ],
    "abort": [
      "param",
      "priority"
    ],
    "getResponse": [
      "body"
    ]
  },
  "headersArray": [
    "headers"
  ],
  "handleError": [
    "error"
  ],
  "HTTPResponse": {
    "constructor": [],
    "remoteAddress": [],
    "url": [],
    "ok": [],
    "status": [],
    "statusText": [],
    "headers": [],
    "securityDetails": [],
    "timing": [],
    "content": [],
    "buffer": [],
    "text": [],
    "json": [],
    "request": [],
    "fromCache": [],
    "fromServiceWorker": [],
    "frame": []
  },
  "Keyboard": {
    "constructor": [],
    "down": [
      "key",
      "options"
    ],
    "up": [
      "key"
    ],
    "sendCharacter": [
      "char"
    ],
    "type": [
      "text",
      "options"
    ],
    "press": [
      "key",
      "options"
    ]
  },
  "Mouse": {
    "constructor": [],
    "reset": [],
    "move": [
      "x",
      "y",
      "options"
    ],
    "down": [
      "options"
    ],
    "up": [
      "options"
    ],
    "click": [
      "x",
      "y",
      "options"
    ],
    "wheel": [
      "options"
    ],
    "drag": [
      "start",
      "target"
    ],
    "dragEnter": [
      "target",
      "data"
    ],
    "dragOver": [
      "target",
      "data"
    ],
    "drop": [
      "target",
      "data"
    ],
    "dragAndDrop": [
      "start",
      "target",
      "options"
    ]
  },
  "Touchscreen": {
    "idGenerator": [],
    "touches": [],
    "constructor": [],
    "removeHandle": [
      "handle"
    ],
    "tap": [
      "x",
      "y"
    ],
    "touchStart": [
      "x",
      "y"
    ],
    "touchMove": [
      "x",
      "y"
    ],
    "touchEnd": []
  },
  "JSHandle": {
    "move": [],
    "_": [],
    "evaluate": [
      "pageFunction",
      "param"
    ],
    "evaluateHandle": [
      "pageFunction",
      "param"
    ],
    "getProperty": [
      "propertyName"
    ],
    "getProperties": [],
    "jsonValue": [],
    "asElement": [],
    "dispose": [],
    "toString": [],
    "remoteObject": []
  },
  "Page": {
    "isServiceWorkerBypassed": [],
    "isDragInterceptionEnabled": [],
    "isJavaScriptEnabled": [],
    "waitForFileChooser": [
      "options"
    ],
    "setGeolocation": [
      "options"
    ],
    "target": [],
    "browser": [],
    "browserContext": [],
    "mainFrame": [],
    "createCDPSession": [],
    "keyboard": [],
    "touchscreen": [],
    "coverage": [],
    "tracing": [],
    "accessibility": [],
    "frames": [],
    "workers": [],
    "setRequestInterception": [
      "value"
    ],
    "setBypassServiceWorker": [
      "bypass"
    ],
    "setDragInterception": [
      "enabled"
    ],
    "setOfflineMode": [
      "enabled"
    ],
    "emulateNetworkConditions": [
      "networkConditions"
    ],
    "setDefaultNavigationTimeout": [
      "timeout"
    ],
    "setDefaultTimeout": [
      "timeout"
    ],
    "getDefaultTimeout": [],
    "getDefaultNavigationTimeout": [],
    "locator": [
      "func"
    ],
    "$": [
      "selector"
    ],
    "$$": [
      "selector",
      "options"
    ],
    "evaluateHandle": [
      "pageFunction",
      "param"
    ],
    "queryObjects": [
      "prototypeHandle"
    ],
    "$eval": [
      "selector",
      "pageFunction",
      "param"
    ],
    "$$eval": [
      "selector",
      "pageFunction",
      "param"
    ],
    "cookies": [
      "param"
    ],
    "deleteCookie": [
      "param"
    ],
    "setCookie": [
      "param"
    ],
    "addScriptTag": [
      "options"
    ],
    "addStyleTag": [
      "options"
    ],
    "exposeFunction": [
      "name",
      "pptrFunction"
    ],
    "removeExposedFunction": [
      "name"
    ],
    "authenticate": [
      "credentials"
    ],
    "setExtraHTTPHeaders": [
      "headers"
    ],
    "setUserAgent": [
      "options"
    ],
    "metrics": [],
    "captureHeapSnapshot": [
      "options"
    ],
    "url": [],
    "content": [],
    "setContent": [
      "html",
      "options"
    ],
    "goto": [
      "url",
      "options"
    ],
    "reload": [
      "options"
    ],
    "waitForNavigation": [
      "options"
    ],
    "waitForRequest": [
      "urlOrPredicate",
      "options"
    ],
    "waitForResponse": [
      "urlOrPredicate",
      "options"
    ],
    "waitForNetworkIdle": [
      "options"
    ],
    "waitForFrame": [
      "urlOrPredicate",
      "options"
    ],
    "goBack": [
      "options"
    ],
    "goForward": [
      "options"
    ],
    "bringToFront": [],
    "emulate": [
      "device"
    ],
    "setJavaScriptEnabled": [
      "enabled"
    ],
    "setBypassCSP": [
      "enabled"
    ],
    "emulateMediaType": [
      "type"
    ],
    "emulateCPUThrottling": [
      "factor"
    ],
    "emulateMediaFeatures": [
      "features"
    ],
    "emulateTimezone": [
      "timezoneId"
    ],
    "emulateIdleState": [
      "overrides"
    ],
    "emulateVisionDeficiency": [
      "type"
    ],
    "setViewport": [
      "viewport"
    ],
    "viewport": [],
    "evaluate": [
      "pageFunction",
      "param"
    ],
    "evaluateOnNewDocument": [
      "pageFunction",
      "param"
    ],
    "removeScriptToEvaluateOnNewDocument": [
      "identifier"
    ],
    "setCacheEnabled": [
      "enabled"
    ],
    "screencast": [
      "options"
    ],
    "screenshot": [
      "options"
    ],
    "emulateFocusedPage": [
      "enabled"
    ],
    "createPDFStream": [
      "options"
    ],
    "pdf": [
      "options"
    ],
    "title": [],
    "close": [
      "options"
    ],
    "isClosed": [],
    "mouse": [],
    "click": [
      "selector",
      "options"
    ],
    "focus": [
      "selector"
    ],
    "hover": [
      "selector"
    ],
    "select": [
      "selector",
      "param"
    ],
    "tap": [
      "selector"
    ],
    "type": [
      "selector",
      "text",
      "options"
    ],
    "waitForSelector": [
      "selector",
      "options"
    ],
    "waitForFunction": [
      "pageFunction",
      "options",
      "param"
    ],
    "waitForDevicePrompt": [
      "options"
    ],
    "resize": [
      "params"
    ],
    "windowId": [],
    "openDevTools": [],
    "bluetooth": []
  },
  "setDefaultScreenshotOptions": [
    "options"
  ],
  "normalizeRectangle": [
    "clip"
  ],
  "roundRectangle": [
    "clip"
  ],
  "Realm": {
    "timeoutSettings": [],
    "taskManager": [],
    "constructor": [
      "timeoutSettings"
    ],
    "environment": [],
    "adoptHandle": [
      "handle"
    ],
    "transferHandle": [
      "handle"
    ],
    "evaluateHandle": [
      "pageFunction",
      "param"
    ],
    "evaluate": [
      "pageFunction",
      "param"
    ],
    "waitForFunction": [
      "pageFunction",
      "param",
      "param"
    ],
    "adoptBackendNode": [
      "backendNodeId"
    ],
    "disposed": [],
    "dispose": [],
    "disposeSymbol": []
  },
  "Target": {
    "constructor": [],
    "worker": [],
    "page": [],
    "asPage": [],
    "url": [],
    "createCDPSession": [],
    "type": [],
    "browser": [],
    "browserContext": [],
    "opener": []
  },
  "WebWorker": {
    "timeoutSettings": [],
    "constructor": [
      "url"
    ],
    "mainRealm": [],
    "url": [],
    "client": [],
    "evaluate": [
      "func",
      "param"
    ],
    "evaluateHandle": [
      "func",
      "param"
    ],
    "close": []
  },
  "Locator": {
    "race": [
      "locators"
    ],
    "_": [],
    "visibility": [],
    "_timeout": [],
    "operators": [],
    "timeout": [],
    "setTimeout": [
      "timeout"
    ],
    "setVisibility": [
      "this",
      "visibility"
    ],
    "setWaitForEnabled": [
      "this",
      "value"
    ],
    "setEnsureElementIsInTheViewport": [
      "this",
      "value"
    ],
    "setWaitForStableBoundingBox": [
      "this",
      "value"
    ],
    "copyOptions": [
      "locator"
    ],
    "_clone": [],
    "_wait": [
      "options"
    ],
    "clone": [],
    "waitHandle": [
      "options"
    ],
    "wait": [
      "options"
    ],
    "map": [
      "mapper"
    ],
    "filter": [
      "predicate"
    ],
    "filterHandle": [
      "predicate"
    ],
    "mapHandle": [
      "mapper"
    ],
    "click": [
      "this",
      "options"
    ],
    "fill": [
      "this",
      "value",
      "options"
    ],
    "hover": [
      "this",
      "options"
    ],
    "scroll": [
      "this",
      "options"
    ]
  },
  "FunctionLocator": {
    "create": [
      "pageOrFrame",
      "func"
    ],
    "constructor": [
      "pageOrFrame",
      "func"
    ],
    "_clone": [],
    "_wait": [
      "options"
    ]
  },
  "DelegatedLocator": {
    "constructor": [
      "delegate"
    ],
    "delegate": [],
    "setTimeout": [
      "timeout"
    ],
    "setVisibility": [
      "this",
      "visibility"
    ],
    "setWaitForEnabled": [
      "this",
      "value"
    ],
    "setEnsureElementIsInTheViewport": [
      "this",
      "value"
    ],
    "setWaitForStableBoundingBox": [
      "this",
      "value"
    ],
    "_clone": [],
    "_wait": []
  },
  "FilteredLocator": {
    "constructor": [
      "base",
      "predicate"
    ],
    "_clone": [],
    "_wait": [
      "options"
    ]
  },
  "MappedLocator": {
    "constructor": [
      "base",
      "mapper"
    ],
    "_clone": [],
    "_wait": [
      "options"
    ]
  },
  "NodeLocator": {
    "create": [
      "pageOrFrame",
      "selector"
    ],
    "createFromHandle": [
      "pageOrFrame",
      "handle"
    ],
    "constructor": [
      "pageOrFrame",
      "selectorOrHandle"
    ],
    "_clone": [],
    "_wait": [
      "options"
    ]
  },
  "RaceLocator": {
    "create": [
      "locators"
    ],
    "constructor": [
      "locators"
    ],
    "_clone": [],
    "_wait": [
      "options"
    ]
  },
  "fillDirectly": [],
  "checkLocatorArray": [
    "locators"
  ],
  "ownKeys": [
    "o"
  ],
  "bidiServerLogger": [
    "prefix",
    "param"
  ],
  "connectBidiOverCdp": [
    "cdp"
  ],
  "CdpConnectionAdapter": {
    "constructor": [
      "cdp"
    ],
    "browserClient": [],
    "getCdpClient": [
      "id"
    ],
    "close": []
  },
  "CDPClientAdapter": {
    "sessionId": [],
    "constructor": [
      "client",
      "sessionId",
      "browserClient"
    ],
    "browserClient": [],
    "sendCommand": [
      "method",
      "param"
    ],
    "close": [],
    "isCloseError": [
      "error"
    ]
  },
  "NoOpTransport": {
    "emitMessage": [
      "message"
    ],
    "setOnMessage": [
      "onMessage"
    ],
    "sendMessage": [
      "message"
    ],
    "close": []
  },
  "BidiBluetoothEmulation": {
    "constructor": [
      "contextId",
      "session"
    ],
    "emulateAdapter": [
      "state",
      "param"
    ],
    "disableEmulation": [],
    "simulatePreconnectedPeripheral": [
      "preconnectedPeripheral"
    ]
  },
  "BidiBrowser": {
    "protocol": [],
    "subscribeModules": [],
    "subscribeCdpEvents": [],
    "create": [
      "opts"
    ],
    "constructor": [],
    "cdpSupported": [],
    "cdpConnection": [],
    "userAgent": [],
    "connection": [],
    "wsEndpoint": [],
    "close": [],
    "connected": [],
    "process": [],
    "createBrowserContext": [
      "options"
    ],
    "version": [],
    "browserContexts": [],
    "defaultBrowserContext": [],
    "newPage": [
      "options"
    ],
    "installExtension": [
      "path"
    ],
    "uninstallExtension": [
      "id"
    ],
    "screens": [],
    "addScreen": [
      "_params"
    ],
    "removeScreen": [
      "_screenId"
    ],
    "getWindowBounds": [
      "windowId"
    ],
    "setWindowBounds": [
      "windowId",
      "windowBounds"
    ],
    "targets": [],
    "target": [],
    "disconnect": [],
    "debugInfo": [],
    "isNetworkEnabled": []
  },
  "_connectToBiDiBrowser": [
    "connectionTransport",
    "url",
    "options"
  ],
  "getBiDiConnection": [
    "connectionTransport",
    "url",
    "options"
  ],
  "BidiCdpSession": {
    "sessions": [],
    "frame": [],
    "constructor": [
      "frame",
      "sessionId"
    ],
    "connection": [],
    "detached": [],
    "send": [
      "method",
      "params",
      "options"
    ],
    "detach": [],
    "onClose": [],
    "id": []
  },
  "BidiConnection": {
    "constructor": [
      "url",
      "transport",
      "idGenerator",
      "param",
      "timeout"
    ],
    "closed": [],
    "url": [],
    "pipeTo": [
      "emitter"
    ],
    "emit": [
      "type",
      "event"
    ],
    "send": [
      "method",
      "params",
      "timeout"
    ],
    "onMessage": [
      "message"
    ],
    "unbind": [],
    "dispose": [],
    "getPendingProtocolErrors": []
  },
  "createProtocolError": [
    "object"
  ],
  "isCdpEvent": [
    "event"
  ],
  "BidiDeserializer": {
    "deserialize": [
      "result"
    ]
  },
  "BidiDeviceRequestPromptManager": {
    "constructor": [
      "contextId",
      "session"
    ],
    "waitForDevicePrompt": [
      "timeout",
      "signal"
    ]
  },
  "BidiDeviceRequestPrompt": {
    "constructor": [
      "contextId",
      "promptId",
      "session",
      "devices"
    ],
    "cancel": [],
    "select": [
      "device"
    ],
    "waitForDevice": []
  },
  "onRequestDevicePromptUpdated": [
    "params"
  ],
  "BidiDialog": {
    "from": [
      "prompt"
    ],
    "constructor": [
      "prompt"
    ],
    "handle": [
      "options"
    ]
  },
  "BidiElementHandle": {
    "from": [
      "value",
      "realm"
    ],
    "handle": [],
    "constructor": [
      "value",
      "realm"
    ],
    "realm": [],
    "frame": [],
    "remoteValue": [],
    "autofill": [
      "data"
    ],
    "contentFrame": [
      "this"
    ],
    "uploadFile": [
      "this",
      "param"
    ],
    "queryAXTree": [
      "this",
      "name",
      "role"
    ],
    "backendNodeId": []
  },
  "ExposableFunction": {
    "from": [
      "frame",
      "name",
      "apply",
      "param"
    ],
    "name": [],
    "constructor": [
      "frame",
      "name",
      "apply",
      "param"
    ]
  },
  "BidiFrame": {
    "from": [
      "parent",
      "browsingContext"
    ],
    "browsingContext": [],
    "realms": [],
    "_id": [],
    "client": [],
    "accessibility": [],
    "constructor": [],
    "timeoutSettings": [],
    "mainRealm": [],
    "isolatedRealm": [],
    "realm": [
      "id"
    ],
    "page": [],
    "url": [],
    "parentFrame": [],
    "childFrames": [],
    "goto": [
      "url",
      "options"
    ],
    "setContent": [
      "html",
      "options"
    ],
    "waitForNavigation": [
      "options"
    ],
    "waitForDevicePrompt": [
      "options"
    ],
    "detached": [],
    "exposeFunction": [
      "name",
      "apply"
    ],
    "removeExposedFunction": [
      "name"
    ],
    "createCDPSession": [],
    "setFiles": [
      "element",
      "files"
    ],
    "frameElement": [],
    "locateNodes": [
      "element",
      "locator"
    ]
  },
  "convertConsoleMessageLevel": [
    "method"
  ],
  "requestFinished$": [
    "request"
  ],
  "isConsoleLogEntry": [
    "event"
  ],
  "isJavaScriptLogEntry": [
    "event"
  ],
  "getStackTraceLocations": [
    "stackTrace"
  ],
  "BidiHTTPRequest": {
    "from": [
      "bidiRequest",
      "frame",
      "isNetworkInterceptionEnabled",
      "redirect"
    ],
    "id": [],
    "constructor": [
      "request",
      "frame",
      "isNetworkInterceptionEnabled",
      "redirect"
    ],
    "client": [],
    "canBeIntercepted": [],
    "interceptResolutionState": [],
    "url": [],
    "resourceType": [],
    "method": [],
    "postData": [],
    "hasPostData": [],
    "fetchPostData": [],
    "headers": [],
    "response": [],
    "failure": [],
    "isNavigationRequest": [],
    "initiator": [],
    "redirectChain": [],
    "frame": [],
    "_continue": [
      "param"
    ],
    "_abort": [],
    "_respond": [
      "response",
      "_priority"
    ],
    "timing": [],
    "getResponseContent": []
  },
  "getBidiHeaders": [
    "rawHeaders"
  ],
  "BidiHTTPResponse": {
    "from": [
      "data",
      "request",
      "cdpSupported"
    ],
    "constructor": [],
    "remoteAddress": [],
    "url": [],
    "status": [],
    "statusText": [],
    "headers": [],
    "request": [],
    "fromCache": [],
    "timing": [],
    "frame": [],
    "fromServiceWorker": [],
    "securityDetails": [],
    "content": []
  },
  "BidiKeyboard": {
    "constructor": [
      "page"
    ],
    "down": [
      "key",
      "_options"
    ],
    "up": [
      "key"
    ],
    "press": [
      "key",
      "param"
    ],
    "type": [
      "text",
      "param"
    ],
    "sendCharacter": [
      "char"
    ]
  },
  "BidiMouse": {
    "constructor": [
      "page"
    ],
    "reset": [],
    "move": [
      "x",
      "y",
      "param"
    ],
    "down": [
      "param"
    ],
    "up": [
      "param"
    ],
    "click": [
      "x",
      "y",
      "param"
    ],
    "wheel": [
      "param"
    ],
    "drag": [],
    "dragOver": [],
    "dragEnter": [],
    "drop": [],
    "dragAndDrop": []
  },
  "BidiTouchHandle": {
    "constructor": [
      "page",
      "touchScreen",
      "id",
      "x",
      "y",
      "properties"
    ],
    "start": [
      "param"
    ],
    "move": [
      "x",
      "y"
    ],
    "end": []
  },
  "BidiTouchscreen": {
    "touches": [],
    "constructor": [
      "page"
    ],
    "touchStart": [
      "x",
      "y",
      "param"
    ]
  },
  "getBidiKeyValue": [
    "key"
  ],
  "getBidiButton": [
    "button"
  ],
  "BidiJSHandle": {
    "from": [
      "value",
      "realm"
    ],
    "realm": [],
    "constructor": [
      "value",
      "realm"
    ],
    "disposed": [],
    "jsonValue": [],
    "asElement": [],
    "dispose": [],
    "isPrimitiveValue": [],
    "toString": [],
    "id": [],
    "remoteValue": [],
    "remoteObject": []
  },
  "evaluationExpression": [
    "fun",
    "param"
  ],
  "testUrlMatchCookieHostname": [
    "cookie",
    "normalizedUrl"
  ],
  "testUrlMatchCookiePath": [
    "cookie",
    "normalizedUrl"
  ],
  "testUrlMatchCookie": [
    "cookie",
    "url"
  ],
  "bidiToPuppeteerCookie": [
    "bidiCookie",
    "param"
  ],
  "getPartitionKey": [],
  "cdpSpecificCookiePropertiesFromBidiToPuppeteer": [
    "bidiCookie",
    "param"
  ],
  "cdpSpecificCookiePropertiesFromPuppeteerToBidi": [
    "cookieParam",
    "param"
  ],
  "convertCookiesSameSiteBiDiToCdp": [
    "sameSite"
  ],
  "convertCookiesSameSiteCdpToBiDi": [
    "sameSite"
  ],
  "convertCookiesExpiryCdpToBiDi": [
    "expiry"
  ],
  "convertCookiesPartitionKeyFromPuppeteerToBiDi": [
    "partitionKey"
  ],
  "BidiRealm": {
    "realm": [],
    "constructor": [
      "realm",
      "timeoutSettings"
    ],
    "initialize": [],
    "internalPuppeteerUtil": [],
    "puppeteerUtil": [],
    "evaluateHandle": [
      "pageFunction",
      "param"
    ],
    "evaluate": [
      "pageFunction",
      "param"
    ],
    "createHandle": [
      "result"
    ],
    "serializeAsync": [
      "arg"
    ],
    "serialize": [
      "arg"
    ],
    "destroyHandles": [
      "handles"
    ],
    "adoptHandle": [
      "handle"
    ],
    "transferHandle": [
      "handle"
    ]
  },
  "BidiFrameRealm": {
    "from": [
      "realm",
      "frame"
    ],
    "realm": [],
    "constructor": [
      "realm",
      "frame"
    ],
    "puppeteerUtil": [],
    "sandbox": [],
    "environment": [],
    "adoptBackendNode": [
      "backendNodeId"
    ]
  },
  "BidiWorkerRealm": {
    "from": [
      "realm",
      "worker"
    ],
    "realm": [],
    "constructor": [
      "realm",
      "frame"
    ],
    "environment": [],
    "adoptBackendNode": []
  },
  "BidiSerializer": {
    "serialize": [
      "arg"
    ]
  },
  "UnserializableError": {},
  "BidiBrowserTarget": {
    "constructor": [
      "browser"
    ],
    "asPage": [],
    "url": [],
    "createCDPSession": [],
    "type": [],
    "browser": [],
    "browserContext": [],
    "opener": []
  },
  "BidiPageTarget": {
    "constructor": [
      "page"
    ],
    "page": [],
    "asPage": [],
    "url": [],
    "createCDPSession": [],
    "type": [],
    "browser": [],
    "browserContext": [],
    "opener": []
  },
  "BidiFrameTarget": {
    "constructor": [
      "frame"
    ],
    "page": [],
    "asPage": [],
    "url": [],
    "createCDPSession": [],
    "type": [],
    "browser": [],
    "browserContext": [],
    "opener": []
  },
  "BidiWorkerTarget": {
    "constructor": [
      "worker"
    ],
    "page": [],
    "asPage": [],
    "url": [],
    "createCDPSession": [],
    "type": [],
    "browser": [],
    "browserContext": [],
    "opener": []
  },
  "BidiWebWorker": {
    "from": [
      "frame",
      "realm"
    ],
    "constructor": [
      "frame",
      "realm"
    ],
    "frame": [],
    "mainRealm": [],
    "client": []
  },
  "BrowsingContext": {
    "from": [
      "userContext",
      "parent",
      "id",
      "url",
      "originalOpener",
      "clientWindow"
    ],
    "defaultRealm": [],
    "id": [],
    "parent": [],
    "userContext": [],
    "originalOpener": [],
    "windowId": [],
    "constructor": [],
    "children": [],
    "closed": [],
    "disposed": [],
    "realms": [],
    "top": [],
    "url": [],
    "dispose": [],
    "activate": [],
    "captureScreenshot": [
      "options"
    ],
    "close": [
      "promptUnload"
    ],
    "traverseHistory": [
      "delta"
    ],
    "navigate": [
      "url",
      "wait"
    ],
    "reload": [
      "options"
    ],
    "setCacheBehavior": [
      "cacheBehavior"
    ],
    "print": [
      "options"
    ],
    "handleUserPrompt": [
      "options"
    ],
    "setViewport": [
      "options"
    ],
    "setTouchOverride": [
      "maxTouchPoints"
    ],
    "performActions": [
      "actions"
    ],
    "releaseActions": [],
    "createWindowRealm": [
      "sandbox"
    ],
    "addPreloadScript": [
      "functionDeclaration",
      "options"
    ],
    "addIntercept": [
      "options"
    ],
    "removePreloadScript": [
      "script"
    ],
    "setGeolocationOverride": [
      "options"
    ],
    "setTimezoneOverride": [
      "timezoneId"
    ],
    "setScreenOrientationOverride": [
      "screenOrientation"
    ],
    "getCookies": [
      "options"
    ],
    "setCookie": [
      "cookie"
    ],
    "setFiles": [
      "element",
      "files"
    ],
    "subscribe": [
      "events"
    ],
    "addInterception": [
      "events"
    ],
    "disposeSymbol": [],
    "deleteCookie": [
      "param"
    ],
    "locateNodes": [
      "locator",
      "startNodes"
    ],
    "setJavaScriptEnabled": [
      "enabled"
    ],
    "isJavaScriptEnabled": [],
    "setUserAgent": [
      "userAgent"
    ],
    "setClientHintsOverride": [
      "clientHints"
    ],
    "setOfflineMode": [
      "enabled"
    ],
    "bluetooth": [],
    "waitForDevicePrompt": [
      "timeout",
      "signal"
    ],
    "setExtraHTTPHeaders": [
      "headers"
    ]
  },
  "Navigation": {
    "from": [
      "context"
    ],
    "constructor": [],
    "disposed": [],
    "request": [],
    "navigation": [],
    "dispose": [],
    "disposeSymbol": []
  },
  "WindowRealm": {
    "from": [
      "context",
      "sandbox"
    ],
    "browsingContext": [],
    "sandbox": [],
    "constructor": [
      "context",
      "sandbox"
    ],
    "session": [],
    "target": []
  },
  "DedicatedWorkerRealm": {
    "from": [
      "owner",
      "id",
      "origin"
    ],
    "owners": [],
    "constructor": [
      "owner",
      "id",
      "origin"
    ],
    "session": []
  },
  "SharedWorkerRealm": {
    "from": [
      "browser",
      "id",
      "origin"
    ],
    "browser": [],
    "constructor": [
      "browser",
      "id",
      "origin"
    ],
    "session": []
  },
  "Request": {
    "from": [
      "browsingContext",
      "event"
    ],
    "constructor": [],
    "disposed": [],
    "error": [],
    "headers": [],
    "id": [],
    "initiator": [],
    "method": [],
    "navigation": [],
    "redirect": [],
    "lastRedirect": [],
    "response": [],
    "url": [],
    "isBlocked": [],
    "resourceType": [],
    "postData": [],
    "hasPostData": [],
    "continueRequest": [
      "param"
    ],
    "failRequest": [],
    "provideResponse": [
      "param"
    ],
    "fetchPostData": [],
    "getResponseContent": [],
    "continueWithAuth": [
      "parameters"
    ],
    "dispose": [],
    "disposeSymbol": [],
    "timing": []
  },
  "UserContext": {
    "DEFAULT": [],
    "create": [
      "browser",
      "id"
    ],
    "browser": [],
    "constructor": [],
    "browsingContexts": [],
    "closed": [],
    "disposed": [],
    "id": [],
    "dispose": [],
    "createBrowsingContext": [
      "type",
      "options"
    ],
    "remove": [],
    "getCookies": [
      "options",
      "sourceOrigin"
    ],
    "setCookie": [
      "cookie",
      "sourceOrigin"
    ],
    "setPermissions": [
      "origin",
      "descriptor",
      "state"
    ],
    "disposeSymbol": []
  },
  "UserPrompt": {
    "from": [
      "browsingContext",
      "info"
    ],
    "browsingContext": [],
    "info": [],
    "constructor": [],
    "closed": [],
    "disposed": [],
    "handled": [],
    "result": [],
    "dispose": [],
    "handle": [
      "options"
    ],
    "disposeSymbol": []
  },
  "createEvaluationError": [
    "details"
  ],
  "rewriteNavigationError": [
    "message",
    "ms"
  ],
  "Accessibility": {
    "constructor": [
      "realm",
      "param"
    ],
    "snapshot": [
      "param"
    ],
    "serializeTree": [
      "node",
      "interestingNodes"
    ],
    "collectInterestingNodes": [
      "collection",
      "node",
      "insideControl"
    ]
  },
  "populateIframes": [
    "root"
  ],
  "AXNode": {
    "payload": [],
    "children": [],
    "iframeSnapshot": [],
    "constructor": [
      "realm",
      "payload"
    ],
    "find": [
      "predicate"
    ],
    "isLeafNode": [],
    "isControl": [],
    "isLandmark": [],
    "isInteresting": [
      "insideControl"
    ],
    "serialize": [],
    "createTree": [
      "realm",
      "payloads"
    ]
  },
  "getUserStringPropertyValue": [
    "key"
  ],
  "getBooleanPropertyValue": [
    "key"
  ],
  "getNumericalPropertyValue": [
    "key"
  ],
  "getTokenPropertyValue": [
    "key"
  ],
  "Binding": {
    "constructor": [
      "name",
      "fn",
      "initSource"
    ],
    "name": [],
    "initSource": [],
    "run": [
      "context",
      "id",
      "args",
      "isTrivial"
    ]
  },
  "CdpBluetoothEmulation": {
    "constructor": [
      "connection"
    ],
    "emulateAdapter": [
      "state",
      "param"
    ],
    "disableEmulation": [],
    "simulatePreconnectedPeripheral": [
      "preconnectedPeripheral"
    ]
  },
  "CdpBrowser": {
    "protocol": [],
    "_create": [
      "connection",
      "contextIds",
      "acceptInsecureCerts",
      "defaultViewport",
      "downloadBehavior",
      "process",
      "closeCallback",
      "targetFilterCallback",
      "isPageTargetCallback",
      "param",
      "param",
      "param"
    ],
    "constructor": [
      "connection",
      "contextIds",
      "defaultViewport",
      "process",
      "closeCallback",
      "targetFilterCallback",
      "isPageTargetCallback",
      "param",
      "param",
      "param"
    ],
    "_attach": [
      "downloadBehavior"
    ],
    "_detach": [],
    "process": [],
    "_targetManager": [],
    "_getIsPageTargetCallback": [],
    "createBrowserContext": [
      "param"
    ],
    "browserContexts": [],
    "defaultBrowserContext": [],
    "_disposeContext": [
      "contextId"
    ],
    "wsEndpoint": [],
    "newPage": [
      "options"
    ],
    "_createPageInContext": [
      "contextId",
      "options"
    ],
    "_createDevToolsPage": [
      "pageTargetId"
    ],
    "installExtension": [
      "path"
    ],
    "uninstallExtension": [
      "id"
    ],
    "screens": [],
    "addScreen": [
      "params"
    ],
    "removeScreen": [
      "screenId"
    ],
    "getWindowBounds": [
      "windowId"
    ],
    "setWindowBounds": [
      "windowId",
      "windowBounds"
    ],
    "targets": [],
    "target": [],
    "version": [],
    "userAgent": [],
    "close": [],
    "disconnect": [],
    "connected": [],
    "debugInfo": [],
    "isNetworkEnabled": []
  },
  "isDevToolsPageTarget": [
    "url"
  ],
  "createSession": [
    "isAutoAttachEmulated"
  ],
  "_connectToCdpBrowser": [
    "connectionTransport",
    "url",
    "options"
  ],
  "CdpBrowserContext": {
    "constructor": [
      "connection",
      "browser",
      "contextId"
    ],
    "id": [],
    "targets": [],
    "pages": [
      "param"
    ],
    "overridePermissions": [
      "origin",
      "permissions"
    ],
    "setPermission": [
      "origin",
      "param"
    ],
    "clearPermissionOverrides": [],
    "newPage": [
      "options"
    ],
    "browser": [],
    "close": [],
    "cookies": [],
    "setCookie": [
      "param"
    ],
    "setDownloadBehavior": [
      "downloadBehavior"
    ]
  },
  "CdpPreloadScript": {
    "constructor": [
      "mainFrame",
      "id",
      "source"
    ],
    "id": [],
    "source": [],
    "getIdForFrame": [
      "frame"
    ],
    "setIdForFrame": [
      "frame",
      "identifier"
    ]
  },
  "CdpCDPSession": {
    "constructor": [
      "connection",
      "targetType",
      "sessionId",
      "parentSessionId",
      "rawErrors"
    ],
    "setTarget": [
      "target"
    ],
    "target": [],
    "connection": [],
    "detached": [],
    "parentSession": [],
    "send": [
      "method",
      "params",
      "options"
    ],
    "onMessage": [
      "object"
    ],
    "detach": [],
    "onClosed": [],
    "id": [],
    "getPendingProtocolErrors": []
  },
  "Connection": {
    "constructor": [
      "url",
      "transport",
      "param",
      "timeout",
      "param",
      "param"
    ],
    "fromSession": [
      "session"
    ],
    "delay": [],
    "timeout": [],
    "_closed": [],
    "_idGenerator": [],
    "_sessions": [],
    "_session": [
      "sessionId"
    ],
    "session": [
      "sessionId"
    ],
    "url": [],
    "send": [
      "method",
      "params",
      "options"
    ],
    "_rawSend": [
      "callbacks",
      "method",
      "params",
      "sessionId",
      "options"
    ],
    "closeBrowser": [],
    "onMessage": [
      "message"
    ],
    "dispose": [],
    "isAutoAttached": [
      "targetId"
    ],
    "_createSession": [
      "targetInfo",
      "param"
    ],
    "createSession": [
      "targetInfo"
    ],
    "getPendingProtocolErrors": []
  },
  "isTargetClosedError": [
    "error"
  ],
  "Coverage": {
    "constructor": [
      "client"
    ],
    "updateClient": [
      "client"
    ],
    "startJSCoverage": [
      "param"
    ],
    "stopJSCoverage": [],
    "startCSSCoverage": [
      "param"
    ],
    "stopCSSCoverage": []
  },
  "JSCoverage": {
    "constructor": [
      "client"
    ],
    "updateClient": [
      "client"
    ],
    "start": [
      "param"
    ],
    "stop": []
  },
  "CSSCoverage": {
    "constructor": [
      "client"
    ],
    "updateClient": [
      "client"
    ],
    "start": [
      "param"
    ],
    "stop": []
  },
  "convertToDisjointRanges": [
    "nestedRanges"
  ],
  "CdpDeviceRequestPrompt": {
    "constructor": [
      "client",
      "timeoutSettings",
      "firstEvent"
    ],
    "waitForDevice": [
      "filter",
      "param"
    ],
    "select": [
      "device"
    ],
    "cancel": []
  },
  "CdpDeviceRequestPromptManager": {
    "constructor": [
      "client",
      "timeoutSettings"
    ],
    "waitForDevicePrompt": [
      "param"
    ]
  },
  "CdpDialog": {
    "constructor": [
      "client",
      "type",
      "message",
      "param"
    ],
    "handle": [
      "options"
    ]
  },
  "CdpElementHandle": {
    "handle": [],
    "constructor": [
      "world",
      "remoteObject"
    ],
    "realm": [],
    "client": [],
    "remoteObject": [],
    "frame": [],
    "contentFrame": [
      "this"
    ],
    "scrollIntoView": [
      "this"
    ],
    "uploadFile": [
      "this",
      "param"
    ],
    "autofill": [
      "data"
    ],
    "queryAXTree": [
      "name",
      "role"
    ],
    "backendNodeId": []
  },
  "EmulatedState": {
    "constructor": [
      "initialState",
      "clientProvider",
      "updater"
    ],
    "setState": [
      "state"
    ],
    "state": [],
    "sync": []
  },
  "EmulationManager": {
    "constructor": [
      "client"
    ],
    "updateClient": [
      "client"
    ],
    "registerState": [
      "state"
    ],
    "clients": [],
    "registerSpeculativeSession": [
      "client"
    ],
    "javascriptEnabled": [],
    "emulateViewport": [
      "viewport"
    ],
    "emulateIdleState": [
      "overrides"
    ],
    "emulateTimezone": [
      "timezoneId"
    ],
    "emulateVisionDeficiency": [
      "type"
    ],
    "emulateCPUThrottling": [
      "factor"
    ],
    "emulateMediaFeatures": [
      "features"
    ],
    "emulateMediaType": [
      "type"
    ],
    "setGeolocation": [
      "options"
    ],
    "resetDefaultBackgroundColor": [],
    "setTransparentBackgroundColor": [],
    "setJavaScriptEnabled": [
      "enabled"
    ],
    "emulateFocus": [
      "enabled"
    ]
  },
  "ExecutionContext": {
    "constructor": [
      "client",
      "contextPayload",
      "world"
    ],
    "id": [],
    "puppeteerUtil": [],
    "evaluate": [
      "pageFunction",
      "param"
    ],
    "evaluateHandle": [
      "pageFunction",
      "param"
    ],
    "disposeSymbol": []
  },
  "convertArgumentAsync": [
    "context",
    "arg"
  ],
  "convertArgument": [
    "context",
    "arg"
  ],
  "rewriteError": [
    "error",
    "message",
    "originalMessage"
  ],
  "ExtensionTransport": {
    "connectTab": [
      "tabId"
    ],
    "onmessage": [],
    "onclose": [],
    "constructor": [
      "tabId"
    ],
    "send": [
      "message"
    ],
    "close": []
  },
  "CdpFrame": {
    "_frameManager": [],
    "_loaderId": [],
    "_lifecycleEvents": [],
    "_id": [],
    "_parentId": [],
    "accessibility": [],
    "worlds": [],
    "constructor": [
      "frameManager",
      "frameId",
      "parentFrameId",
      "client"
    ],
    "_client": [],
    "updateId": [
      "id"
    ],
    "updateClient": [
      "client"
    ],
    "page": [],
    "goto": [
      "url",
      "options"
    ],
    "waitForNavigation": [
      "options"
    ],
    "client": [],
    "mainRealm": [],
    "isolatedRealm": [],
    "setContent": [
      "html",
      "options"
    ],
    "url": [],
    "parentFrame": [],
    "childFrames": [],
    "addPreloadScript": [
      "preloadScript"
    ],
    "addExposedFunctionBinding": [
      "binding"
    ],
    "removeExposedFunctionBinding": [
      "binding"
    ],
    "waitForDevicePrompt": [
      "options"
    ],
    "_navigated": [
      "framePayload"
    ],
    "_navigatedWithinDocument": [
      "url"
    ],
    "_onLifecycleEvent": [
      "loaderId",
      "name"
    ],
    "_onLoadingStopped": [],
    "_onLoadingStarted": [],
    "detached": [],
    "disposeSymbol": [],
    "exposeFunction": [],
    "frameElement": []
  },
  "navigate": [
    "client",
    "url",
    "referrer",
    "referrerPolicy",
    "frameId"
  ],
  "referrerPolicyToProtocol": [
    "referrerPolicy"
  ],
  "FrameManager": {
    "_frameTree": [],
    "timeoutSettings": [],
    "networkManager": [],
    "client": [],
    "constructor": [
      "client",
      "page",
      "timeoutSettings"
    ],
    "swapFrameTree": [
      "client"
    ],
    "registerSpeculativeSession": [
      "client"
    ],
    "setupEventListeners": [
      "session"
    ],
    "initialize": [
      "client",
      "frame"
    ],
    "page": [],
    "mainFrame": [],
    "frames": [],
    "frame": [
      "frameId"
    ],
    "addExposedFunctionBinding": [
      "binding"
    ],
    "removeExposedFunctionBinding": [
      "binding"
    ],
    "evaluateOnNewDocument": [
      "source"
    ],
    "removeScriptToEvaluateOnNewDocument": [
      "identifier"
    ],
    "onAttachedToTarget": [
      "target"
    ],
    "_deviceRequestPromptManager": [
      "client"
    ]
  },
  "FrameTree": {
    "getMainFrame": [],
    "getById": [
      "frameId"
    ],
    "waitForFrame": [
      "frameId"
    ],
    "frames": [],
    "addFrame": [
      "frame"
    ],
    "removeFrame": [
      "frame"
    ],
    "childFrames": [
      "frameId"
    ],
    "parentFrame": [
      "frameId"
    ]
  },
  "CdpHTTPRequest": {
    "id": [],
    "_redirectChain": [],
    "_response": [],
    "client": [
      "newClient"
    ],
    "constructor": [
      "client",
      "frame",
      "interceptionId",
      "allowInterception",
      "data",
      "redirectChain"
    ],
    "updateHeaders": [
      "headers"
    ],
    "url": [],
    "resourceType": [],
    "method": [],
    "postData": [],
    "hasPostData": [],
    "fetchPostData": [],
    "headers": [],
    "response": [],
    "frame": [],
    "isNavigationRequest": [],
    "initiator": [],
    "redirectChain": [],
    "failure": [],
    "canBeIntercepted": [],
    "_continue": [
      "param"
    ],
    "_respond": [
      "response"
    ],
    "_abort": [
      "errorReason"
    ]
  },
  "CdpHTTPResponse": {
    "constructor": [
      "request",
      "responsePayload",
      "extraInfo"
    ],
    "_resolveBody": [
      "err"
    ],
    "remoteAddress": [],
    "url": [],
    "status": [],
    "statusText": [],
    "headers": [],
    "securityDetails": [],
    "timing": [],
    "content": [],
    "request": [],
    "fromCache": [],
    "fromServiceWorker": [],
    "frame": []
  },
  "CdpKeyboard": {
    "_modifiers": [],
    "constructor": [
      "client"
    ],
    "updateClient": [
      "client"
    ],
    "down": [
      "key",
      "param"
    ],
    "up": [
      "key"
    ],
    "sendCharacter": [
      "char"
    ],
    "charIsKey": [
      "char"
    ],
    "type": [
      "text",
      "param"
    ],
    "press": [
      "key",
      "param"
    ]
  },
  "CdpMouse": {
    "constructor": [
      "client",
      "keyboard"
    ],
    "updateClient": [
      "client"
    ],
    "reset": [],
    "move": [
      "x",
      "y",
      "param"
    ],
    "down": [
      "param"
    ],
    "up": [
      "param"
    ],
    "click": [
      "x",
      "y",
      "param"
    ],
    "wheel": [
      "param"
    ],
    "drag": [
      "start",
      "target"
    ],
    "dragEnter": [
      "target",
      "data"
    ],
    "dragOver": [
      "target",
      "data"
    ],
    "drop": [
      "target",
      "data"
    ],
    "dragAndDrop": [
      "start",
      "target",
      "param"
    ]
  },
  "CdpTouchHandle": {
    "constructor": [
      "client",
      "touchScreen",
      "keyboard",
      "touchPoint"
    ],
    "updateClient": [
      "client"
    ],
    "start": [],
    "move": [
      "x",
      "y"
    ],
    "end": []
  },
  "CdpTouchscreen": {
    "touches": [],
    "constructor": [
      "client",
      "keyboard"
    ],
    "updateClient": [
      "client"
    ],
    "touchStart": [
      "x",
      "y"
    ]
  },
  "getFlag": [
    "button"
  ],
  "getButtonFromPressedButtons": [
    "buttons"
  ],
  "popTransaction": [],
  "IsolatedWorld": {
    "constructor": [
      "frameOrWorker",
      "timeoutSettings"
    ],
    "environment": [],
    "client": [],
    "emitter": [],
    "setContext": [
      "context"
    ],
    "hasContext": [],
    "context": [],
    "evaluateHandle": [
      "pageFunction",
      "param"
    ],
    "evaluate": [
      "pageFunction",
      "param"
    ],
    "adoptBackendNode": [
      "backendNodeId"
    ],
    "adoptHandle": [
      "handle"
    ],
    "transferHandle": [
      "handle"
    ],
    "createCdpHandle": [
      "remoteObject"
    ],
    "disposeSymbol": []
  },
  "CdpJSHandle": {
    "constructor": [
      "world",
      "remoteObject"
    ],
    "disposed": [],
    "realm": [],
    "client": [],
    "jsonValue": [],
    "asElement": [],
    "dispose": [],
    "toString": [],
    "id": [],
    "remoteObject": [],
    "getProperties": []
  },
  "releaseObject": [
    "client",
    "remoteObject"
  ],
  "LifecycleWatcher": {
    "constructor": [
      "networkManager",
      "frame",
      "waitUntil",
      "timeout",
      "signal"
    ],
    "navigationResponse": [],
    "sameDocumentNavigationPromise": [],
    "newDocumentNavigationPromise": [],
    "lifecyclePromise": [],
    "terminationPromise": [],
    "dispose": []
  },
  "checkLifecycle": [
    "frame",
    "expectedLifecycle"
  ],
  "NetworkEventManager": {
    "forget": [
      "networkRequestId"
    ],
    "requestExtraInfo": [
      "networkRequestId"
    ],
    "responseExtraInfo": [
      "networkRequestId"
    ],
    "queuedRedirectInfo": [
      "fetchRequestId"
    ],
    "queueRedirectInfo": [
      "fetchRequestId",
      "redirectInfo"
    ],
    "takeQueuedRedirectInfo": [
      "fetchRequestId"
    ],
    "inFlightRequestsCount": [],
    "storeRequestWillBeSent": [
      "networkRequestId",
      "event"
    ],
    "getRequestWillBeSent": [
      "networkRequestId"
    ],
    "forgetRequestWillBeSent": [
      "networkRequestId"
    ],
    "getRequestPaused": [
      "networkRequestId"
    ],
    "forgetRequestPaused": [
      "networkRequestId"
    ],
    "storeRequestPaused": [
      "networkRequestId",
      "event"
    ],
    "getRequest": [
      "networkRequestId"
    ],
    "storeRequest": [
      "networkRequestId",
      "request"
    ],
    "forgetRequest": [
      "networkRequestId"
    ],
    "getQueuedEventGroup": [
      "networkRequestId"
    ],
    "queueEventGroup": [
      "networkRequestId",
      "event"
    ],
    "forgetQueuedEventGroup": [
      "networkRequestId"
    ],
    "printState": []
  },
  "replacer": [
    "_key",
    "value"
  ],
  "NetworkManager": {
    "constructor": [
      "frameManager",
      "networkEnabled"
    ],
    "addClient": [
      "client"
    ],
    "authenticate": [
      "credentials"
    ],
    "setExtraHTTPHeaders": [
      "headers"
    ],
    "extraHTTPHeaders": [],
    "inFlightRequestsCount": [],
    "setOfflineMode": [
      "value"
    ],
    "emulateNetworkConditions": [
      "networkConditions"
    ],
    "setUserAgent": [
      "userAgent",
      "userAgentMetadata",
      "platform"
    ],
    "setCacheEnabled": [
      "enabled"
    ],
    "setRequestInterception": [
      "value"
    ]
  },
  "CdpPage": {
    "_create": [
      "client",
      "target",
      "defaultViewport"
    ],
    "constructor": [
      "client",
      "target"
    ],
    "resize": [
      "params"
    ],
    "windowId": [],
    "_client": [],
    "isServiceWorkerBypassed": [],
    "isDragInterceptionEnabled": [],
    "isJavaScriptEnabled": [],
    "openDevTools": [],
    "waitForFileChooser": [
      "param"
    ],
    "setGeolocation": [
      "options"
    ],
    "target": [],
    "browser": [],
    "browserContext": [],
    "mainFrame": [],
    "keyboard": [],
    "touchscreen": [],
    "coverage": [],
    "tracing": [],
    "frames": [],
    "workers": [],
    "setRequestInterception": [
      "value"
    ],
    "setBypassServiceWorker": [
      "bypass"
    ],
    "setDragInterception": [
      "enabled"
    ],
    "setOfflineMode": [
      "enabled"
    ],
    "emulateNetworkConditions": [
      "networkConditions"
    ],
    "emulateFocusedPage": [
      "enabled"
    ],
    "setDefaultNavigationTimeout": [
      "timeout"
    ],
    "setDefaultTimeout": [
      "timeout"
    ],
    "getDefaultTimeout": [],
    "getDefaultNavigationTimeout": [],
    "queryObjects": [
      "prototypeHandle"
    ],
    "cookies": [
      "param"
    ],
    "deleteCookie": [
      "param"
    ],
    "setCookie": [
      "param"
    ],
    "exposeFunction": [
      "name",
      "pptrFunction"
    ],
    "removeExposedFunction": [
      "name"
    ],
    "authenticate": [
      "credentials"
    ],
    "setExtraHTTPHeaders": [
      "headers"
    ],
    "setUserAgent": [
      "userAgentOrOptions",
      "userAgentMetadata"
    ],
    "metrics": [],
    "captureHeapSnapshot": [
      "options"
    ],
    "reload": [
      "options"
    ],
    "createCDPSession": [],
    "goBack": [
      "param"
    ],
    "goForward": [
      "param"
    ],
    "bringToFront": [],
    "setJavaScriptEnabled": [
      "enabled"
    ],
    "setBypassCSP": [
      "enabled"
    ],
    "emulateMediaType": [
      "type"
    ],
    "emulateCPUThrottling": [
      "factor"
    ],
    "emulateMediaFeatures": [
      "features"
    ],
    "emulateTimezone": [
      "timezoneId"
    ],
    "emulateIdleState": [
      "overrides"
    ],
    "emulateVisionDeficiency": [
      "type"
    ],
    "setViewport": [
      "viewport"
    ],
    "viewport": [],
    "evaluateOnNewDocument": [
      "pageFunction",
      "param"
    ],
    "removeScriptToEvaluateOnNewDocument": [
      "identifier"
    ],
    "setCacheEnabled": [
      "param"
    ],
    "_screenshot": [
      "options"
    ],
    "createPDFStream": [
      "param"
    ],
    "pdf": [
      "param"
    ],
    "close": [
      "param"
    ],
    "isClosed": [],
    "mouse": [],
    "waitForDevicePrompt": [
      "param"
    ],
    "bluetooth": []
  },
  "convertSameSiteFromPuppeteerToCdp": [
    "sameSite"
  ],
  "filterUnsupportedAttributes": [
    "cookie"
  ],
  "handler": [
    "event"
  ],
  "getIntersectionRect": [
    "clip",
    "viewport"
  ],
  "convertCookiesPartitionKeyFromPuppeteerToCdp": [
    "partitionKey"
  ],
  "CdpTarget": {
    "_initializedDeferred": [],
    "_isClosedDeferred": [],
    "_targetId": [],
    "constructor": [
      "targetInfo",
      "session",
      "browserContext",
      "targetManager",
      "sessionFactory"
    ],
    "asPage": [],
    "_subtype": [],
    "_session": [],
    "_addChildTarget": [
      "target"
    ],
    "_removeChildTarget": [
      "target"
    ],
    "_childTargets": [],
    "_sessionFactory": [],
    "createCDPSession": [],
    "url": [],
    "type": [],
    "_targetManager": [],
    "_getTargetInfo": [],
    "browser": [],
    "browserContext": [],
    "opener": [],
    "_targetInfoChanged": [
      "targetInfo"
    ],
    "_initialize": [],
    "_isTargetExposed": [],
    "_checkIfInitialized": []
  },
  "PageTarget": {
    "pagePromise": [],
    "constructor": [
      "targetInfo",
      "session",
      "browserContext",
      "targetManager",
      "sessionFactory",
      "defaultViewport"
    ],
    "_initialize": [],
    "page": [],
    "_checkIfInitialized": []
  },
  "DevToolsTarget": {},
  "WorkerTarget": {
    "worker": []
  },
  "OtherTarget": {},
  "TargetManager": {
    "constructor": [
      "connection",
      "targetFactory",
      "targetFilterCallback",
      "param"
    ],
    "initialize": [],
    "getChildTargets": [
      "target"
    ],
    "dispose": [],
    "getAvailableTargets": []
  },
  "isPageTargetBecomingPrimary": [
    "target",
    "newTargetInfo"
  ],
  "listener": [
    "event"
  ],
  "detachedListener": [
    "event"
  ],
  "Tracing": {
    "constructor": [
      "client"
    ],
    "updateClient": [
      "client"
    ],
    "start": [
      "param"
    ],
    "stop": []
  },
  "CdpWebWorker": {
    "constructor": [
      "client",
      "url",
      "targetId",
      "targetType",
      "consoleAPICalled",
      "exceptionThrown",
      "networkManager"
    ],
    "mainRealm": [],
    "client": [],
    "close": []
  },
  "getErrorDetails": [
    "details"
  ],
  "createClientError": [
    "details"
  ],
  "valueFromJSHandle": [
    "handle"
  ],
  "valueFromRemoteObjectReference": [
    "handle"
  ],
  "valueFromPrimitiveRemoteObject": [
    "remoteObject"
  ],
  "addPageBinding": [
    "type",
    "name",
    "prefix"
  ],
  "pageBindingInitString": [
    "type",
    "name"
  ],
  "ARIAQueryHandler": {
    "querySelector": [],
    "queryAll": [
      "element",
      "selector"
    ],
    "queryOne": []
  },
  "isKnownAttribute": [
    "attribute"
  ],
  "parseARIASelector": [
    "selector"
  ],
  "getWebSocketTransportClass": [],
  "_connectToBrowser": [
    "options"
  ],
  "getConnectionTransport": [
    "options"
  ],
  "getWSEndpoint": [
    "browserURL"
  ],
  "BrowserWebSocketTransport": {
    "create": [
      "url"
    ],
    "onmessage": [],
    "onclose": [],
    "constructor": [
      "ws"
    ],
    "send": [
      "message"
    ],
    "close": []
  },
  "CSSQueryHandler": {
    "querySelector": [],
    "querySelectorAll": []
  },
  "CallbackRegistry": {
    "constructor": [
      "idGenerator"
    ],
    "create": [
      "label",
      "timeout",
      "request"
    ],
    "reject": [
      "id",
      "message",
      "originalMessage"
    ],
    "rejectRaw": [
      "id",
      "error"
    ],
    "_reject": [
      "callback",
      "errorMessage",
      "originalMessage"
    ],
    "resolve": [
      "id",
      "value"
    ],
    "clear": [],
    "getPendingProtocolErrors": []
  },
  "Callback": {
    "constructor": [
      "id",
      "label",
      "timeout"
    ],
    "resolve": [
      "value"
    ],
    "reject": [
      "error"
    ],
    "id": [],
    "promise": [],
    "error": [],
    "label": []
  },
  "ConsoleMessage": {
    "constructor": [
      "type",
      "text",
      "args",
      "stackTraceLocations",
      "frame",
      "rawStackTrace",
      "targetId"
    ],
    "type": [],
    "text": [],
    "args": [],
    "location": [],
    "stackTrace": [],
    "_rawStackTrace": [],
    "_targetId": []
  },
  "CustomQueryHandlerRegistry": {
    "get": [
      "name"
    ],
    "register": [
      "name",
      "handler"
    ],
    "unregister": [
      "name"
    ],
    "names": [],
    "clear": []
  },
  "importDebug": [],
  "debug": [
    "prefix"
  ],
  "setLogCapture": [
    "value"
  ],
  "getCapturedLogs": [],
  "PuppeteerError": {
    "constructor": [
      "message",
      "options"
    ]
  },
  "TimeoutError": {},
  "TouchError": {},
  "ProtocolError": {
    "code": [],
    "originalMessage": []
  },
  "UnsupportedOperation": {},
  "TargetCloseError": {},
  "ConnectionClosedError": {},
  "EventEmitter": {
    "constructor": [
      "param"
    ],
    "on": [
      "type",
      "handler"
    ],
    "off": [
      "type",
      "handler"
    ],
    "emit": [
      "type",
      "event"
    ],
    "once": [
      "type",
      "handler"
    ],
    "listenerCount": [
      "type"
    ],
    "removeAllListeners": [
      "type"
    ],
    "disposeSymbol": []
  },
  "onceHandler": [
    "eventData"
  ],
  "FileChooser": {
    "constructor": [
      "element",
      "multiple"
    ],
    "isMultiple": [],
    "accept": [
      "paths"
    ],
    "cancel": []
  },
  "getQueryHandlerAndSelector": [
    "selector"
  ],
  "fastTransposeIteratorHandle": [
    "iterator",
    "size"
  ],
  "transposeIteratorHandle": [
    "iterator"
  ],
  "transposeIterableHandle": [
    "handle"
  ],
  "LazyArg": {
    "create": [],
    "constructor": [
      "get"
    ],
    "get": [
      "context"
    ]
  },
  "PQueryHandler": {
    "querySelectorAll": [],
    "querySelector": []
  },
  "unquote": [
    "text"
  ],
  "parsePSelectors": [
    "selector"
  ],
  "PierceQueryHandler": {
    "querySelector": [],
    "querySelectorAll": []
  },
  "Puppeteer": {
    "customQueryHandlers": [],
    "registerCustomQueryHandler": [
      "name",
      "queryHandler"
    ],
    "unregisterCustomQueryHandler": [
      "name"
    ],
    "customQueryHandlerNames": [],
    "clearCustomQueryHandlers": [],
    "_isPuppeteerCore": [],
    "_changedBrowsers": [],
    "constructor": [
      "settings"
    ],
    "connect": [
      "options"
    ]
  },
  "QueryHandler": {
    "querySelectorAll": [],
    "querySelector": [],
    "_querySelector": [],
    "_querySelectorAll": [],
    "queryAll": [
      "element",
      "selector"
    ],
    "queryOne": [
      "element",
      "selector"
    ],
    "waitFor": [
      "elementOrFrame",
      "selector",
      "options"
    ]
  },
  "ScriptInjector": {
    "append": [
      "statement"
    ],
    "pop": [
      "statement"
    ],
    "inject": [
      "inject",
      "param"
    ]
  },
  "SecurityDetails": {
    "constructor": [
      "securityPayload"
    ],
    "issuer": [],
    "validFrom": [],
    "validTo": [],
    "protocol": [],
    "subjectName": [],
    "subjectAlternativeNames": []
  },
  "TaskQueue": {
    "constructor": [],
    "postTask": [
      "task"
    ]
  },
  "TextQueryHandler": {
    "querySelectorAll": []
  },
  "TimeoutSettings": {
    "constructor": [],
    "setDefaultTimeout": [
      "timeout"
    ],
    "setDefaultNavigationTimeout": [
      "timeout"
    ],
    "navigationTimeout": [],
    "timeout": []
  },
  "WaitTask": {
    "constructor": [
      "world",
      "options",
      "fn",
      "param"
    ],
    "result": [],
    "rerun": [],
    "terminate": [
      "error"
    ],
    "getBadError": [
      "error"
    ]
  },
  "TaskManager": {
    "add": [
      "task"
    ],
    "delete": [
      "task"
    ],
    "terminateAll": [
      "error"
    ],
    "rerunAll": []
  },
  "XPathQueryHandler": {
    "querySelectorAll": [],
    "querySelector": []
  },
  "PuppeteerURL": {
    "INTERNAL_URL": [],
    "fromCallSite": [
      "functionName",
      "site"
    ],
    "parse": [],
    "isPuppeteerURL": [],
    "functionName": [],
    "siteString": [],
    "toString": []
  },
  "withSourcePuppeteerURLIfNone": [
    "functionName",
    "object"
  ],
  "getSourcePuppeteerURLIfAvailable": [
    "object"
  ],
  "isString": [
    "obj"
  ],
  "isNumber": [
    "obj"
  ],
  "isPlainObject": [
    "obj"
  ],
  "isRegExp": [
    "obj"
  ],
  "isDate": [
    "obj"
  ],
  "evaluationString": [
    "fun",
    "param"
  ],
  "serializeArgument": [
    "arg"
  ],
  "getReadableAsTypedArray": [
    "readable",
    "path"
  ],
  "getReadableFromProtocolStream": [
    "client",
    "handle"
  ],
  "validateDialogType": [
    "type"
  ],
  "timeout": [
    "ms",
    "cause"
  ],
  "getSourceUrlComment": [
    "url"
  ],
  "parsePDFOptions": [
    "param",
    "param"
  ],
  "convertPrintParameterToInches": [
    "parameter",
    "param"
  ],
  "fromEmitterEvent": [
    "emitter",
    "eventName"
  ],
  "fromAbortSignal": [
    "signal",
    "cause"
  ],
  "filterAsync": [
    "predicate"
  ],
  "ariaQuerySelector": [
    "root",
    "selector"
  ],
  "ariaQuerySelectorAll": [
    "root",
    "selector"
  ],
  "cssQuerySelector": [
    "root",
    "selector"
  ],
  "cssQuerySelectorAll": [
    "root",
    "selector"
  ],
  "CustomQuerySelectorRegistry": {
    "register": [
      "name",
      "handler"
    ],
    "unregister": [
      "name"
    ],
    "get": [
      "name"
    ],
    "clear": []
  },
  "isQueryableNode": [
    "node"
  ],
  "PQueryEngine": {
    "elements": [],
    "constructor": [
      "element",
      "complexSelector"
    ],
    "run": []
  },
  "DepthCalculator": {
    "calculate": [
      "node",
      "param"
    ]
  },
  "compareDepths": [
    "a",
    "b"
  ],
  "domSort": [
    "elements"
  ],
  "pQuerySelectorAll": [
    "root",
    "selector"
  ],
  "pQuerySelector": [
    "root",
    "selector"
  ],
  "pierceQuerySelector": [
    "root",
    "selector"
  ],
  "search": [
    "root"
  ],
  "pierceQuerySelectorAll": [
    "element",
    "selector"
  ],
  "collect": [
    "root"
  ],
  "MutationPoller": {
    "constructor": [
      "fn",
      "root"
    ],
    "start": [],
    "stop": [],
    "result": []
  },
  "RAFPoller": {
    "constructor": [
      "fn"
    ],
    "start": [],
    "stop": [],
    "result": []
  },
  "IntervalPoller": {
    "constructor": [
      "fn",
      "ms"
    ],
    "start": [],
    "stop": [],
    "result": []
  },
  "poll": [],
  "isNonTrivialValueNode": [
    "node"
  ],
  "isSuitableNodeForTextMatching": [
    "node"
  ],
  "eraseFromCache": [
    "node"
  ],
  "createTextContent": [
    "root"
  ],
  "textQuerySelectorAll": [
    "root",
    "selector"
  ],
  "xpathQuerySelectorAll": [
    "root",
    "selector",
    "param"
  ],
  "checkVisibility": [
    "node",
    "visible"
  ],
  "isBoundingBoxEmpty": [
    "element"
  ],
  "hasShadowRoot": [
    "node"
  ],
  "pierce": [
    "root"
  ],
  "pierceAll": [
    "root"
  ],
  "BrowserLauncher": {
    "puppeteer": [],
    "constructor": [
      "puppeteer",
      "browser"
    ],
    "browser": [],
    "launch": [
      "param"
    ],
    "executablePath": [
      "channel",
      "validatePath"
    ],
    "defaultArgs": [
      "object"
    ],
    "computeLaunchArguments": [
      "options"
    ],
    "cleanUserDataDir": [
      "path",
      "opts"
    ],
    "closeBrowser": [
      "browserProcess",
      "cdpConnection"
    ],
    "waitForPageTarget": [
      "browser",
      "timeout"
    ],
    "createCdpSocketConnection": [
      "browserProcess",
      "opts"
    ],
    "createCdpPipeConnection": [
      "browserProcess",
      "opts"
    ],
    "createBiDiOverCdpBrowser": [
      "browserProcess",
      "cdpConnection",
      "closeCallback",
      "opts"
    ],
    "createBiDiBrowser": [
      "browserProcess",
      "closeCallback",
      "opts"
    ],
    "getProfilePath": [],
    "resolveExecutablePath": [
      "headless",
      "param"
    ]
  },
  "onProcessExit": [],
  "browserCloseCallback": [],
  "puppeteerBrowserToInstalledBrowser": [
    "browser",
    "headless"
  ],
  "ChromeLauncher": {
    "constructor": [
      "puppeteer"
    ],
    "launch": [
      "param"
    ],
    "computeLaunchArguments": [
      "param"
    ],
    "cleanUserDataDir": [
      "path",
      "opts"
    ],
    "defaultArgs": [
      "param"
    ],
    "executablePath": [
      "channel",
      "param"
    ]
  },
  "getFeatures": [
    "flag",
    "param"
  ],
  "removeMatchingFlags": [
    "array",
    "flag"
  ],
  "FirefoxLauncher": {
    "constructor": [
      "puppeteer"
    ],
    "getPreferences": [
      "extraPrefsFirefox"
    ],
    "computeLaunchArguments": [
      "param"
    ],
    "cleanUserDataDir": [
      "userDataDir",
      "opts"
    ],
    "executablePath": [
      "_",
      "param"
    ],
    "defaultArgs": [
      "param"
    ]
  },
  "convertPuppeteerChannelToBrowsersChannel": [
    "channel"
  ],
  "NodeWebSocketTransport": {
    "create": [
      "url",
      "headers"
    ],
    "onmessage": [],
    "onclose": [],
    "constructor": [
      "ws"
    ],
    "send": [
      "message"
    ],
    "close": []
  },
  "PipeTransport": {
    "onclose": [],
    "onmessage": [],
    "constructor": [
      "pipeWrite",
      "pipeRead"
    ],
    "send": [
      "message"
    ],
    "close": []
  },
  "PuppeteerNode": {
    "defaultBrowserRevision": [],
    "configuration": [],
    "constructor": [
      "settings"
    ],
    "connect": [
      "options"
    ],
    "launch": [
      "param"
    ],
    "executablePath": [
      "optsOrChannel"
    ],
    "browserVersion": [],
    "defaultDownloadPath": [],
    "lastLaunchedBrowser": [],
    "defaultBrowser": [],
    "product": [],
    "defaultArgs": [
      "param"
    ],
    "trimCache": []
  },
  "ScreenRecorder": {
    "stop": []
  },
  "rm": [
    "path"
  ],
  "rmSync": [
    "path"
  ],
  "AsyncIterableUtil": {
    "map": [
      "iterable",
      "map"
    ],
    "flatMap": [
      "iterable",
      "map"
    ],
    "collect": [
      "iterable"
    ],
    "first": [
      "iterable"
    ]
  },
  "Deferred": {
    "create": [
      "opts"
    ],
    "race": [
      "awaitables"
    ],
    "constructor": [
      "opts"
    ],
    "resolve": [
      "value"
    ],
    "reject": [
      "error"
    ],
    "resolved": [],
    "finished": [],
    "value": [],
    "valueOrThrow": []
  },
  "isErrorLike": [
    "obj"
  ],
  "isErrnoException": [
    "obj"
  ],
  "createProtocolErrorMessage": [
    "object"
  ],
  "createFunction": [
    "functionValue"
  ],
  "stringifyFunction": [
    "fn"
  ],
  "interpolateFunction": [
    "fn",
    "replacements"
  ],
  "Mutex": {
    "Guard": [],
    "acquire": [
      "onRelease"
    ],
    "release": []
  },
  "assert": [
    "value",
    "message"
  ],
  "moveable": [
    "Class",
    "_"
  ],
  "throwIfDisposed": [
    "param"
  ],
  "inertIfDisposed": [
    "target",
    "_"
  ],
  "invokeAtMostOnceForArguments": [
    "target",
    "_"
  ],
  "guarded": [
    "param"
  ],
  "bubbleInitializer": [
    "this",
    "events"
  ],
  "bubble": [
    "events"
  ],
  "DisposableStackPolyfill": {
    "disposed": [],
    "dispose": [],
    "use": [
      "value"
    ],
    "adopt": [
      "value",
      "onDispose"
    ],
    "defer": [
      "onDispose"
    ],
    "move": [],
    "disposeSymbol": []
  },
  "AsyncDisposableStackPolyfill": {
    "disposed": [],
    "disposeAsync": [],
    "use": [
      "value"
    ],
    "adopt": [
      "value",
      "onDispose"
    ],
    "defer": [
      "onDispose"
    ],
    "move": [],
    "asyncDisposeSymbol": []
  },
  "SuppressedErrorPolyfill": {
    "constructor": [
      "error",
      "suppressed",
      "param"
    ],
    "error": [],
    "suppressed": []
  },
  "stringToTypedArray": [
    "string",
    "param"
  ],
  "stringToBase64": [
    "str"
  ],
  "typedArrayToBase64": [
    "typedArray"
  ],
  "mergeUint8Arrays": [
    "items"
  ],
  "createIncrementalIdGenerator": [],
  "__esm": [
    "fn",
    "res"
  ],
  "__export": [
    "target",
    "all"
  ],
  "__copyProps": [
    "to",
    "from",
    "except",
    "desc"
  ],
  "__toCommonJS": [
    "mod"
  ],
  "mitt_default": [
    "n"
  ],
  "getArgumentPatternByType": [
    "type"
  ],
  "gobbleParens": [
    "text",
    "offset"
  ],
  "tokenizeBy": [
    "text",
    "param"
  ],
  "tokenize": [
    "selector",
    "param"
  ],
  "stringify": [
    "listOrNode"
  ],
  "__commonJS": [
    "cb",
    "mod"
  ],
  "isFunction": [
    "value"
  ],
  "createErrorClass": [
    "createImpl"
  ],
  "_super": [
    "instance"
  ],
  "arrRemove": [
    "arr",
    "item"
  ],
  "Subscription2": [
    "initialTeardown"
  ],
  "isSubscription": [
    "value"
  ],
  "execFinalizer": [
    "finalizer"
  ],
  "reportUnhandledError": [
    "err"
  ],
  "noop": [],
  "errorNotification": [
    "error"
  ],
  "nextNotification": [
    "value"
  ],
  "createNotification": [
    "kind",
    "value",
    "error"
  ],
  "errorContext": [
    "cb"
  ],
  "captureError": [
    "err"
  ],
  "extendStatics": [
    "d",
    "b"
  ],
  "__": [],
  "Subscriber2": [
    "destination"
  ],
  "bind": [
    "fn",
    "thisArg"
  ],
  "ConsumerObserver2": [
    "partialObserver"
  ],
  "SafeSubscriber2": [
    "observerOrNext",
    "error",
    "complete"
  ],
  "handleUnhandledError": [
    "error"
  ],
  "defaultErrorHandler": [
    "err"
  ],
  "handleStoppedNotification": [
    "notification",
    "subscriber"
  ],
  "identity": [
    "x"
  ],
  "pipe": [],
  "pipeFromArray": [
    "fns"
  ],
  "Observable2": [
    "subscribe"
  ],
  "getPromiseCtor": [
    "promiseCtor"
  ],
  "isObserver": [
    "value"
  ],
  "isSubscriber": [
    "value"
  ],
  "hasLift": [
    "source"
  ],
  "operate": [
    "init"
  ],
  "createOperatorSubscriber": [
    "destination",
    "onNext",
    "onComplete",
    "onError",
    "onFinalize"
  ],
  "OperatorSubscriber2": [
    "destination",
    "onNext",
    "onComplete",
    "onError",
    "onFinalize",
    "shouldUnsubscribe"
  ],
  "refCount": [],
  "ConnectableObservable2": [
    "source",
    "subjectFactory"
  ],
  "animationFrames": [
    "timestampProvider"
  ],
  "animationFramesFactory": [
    "timestampProvider"
  ],
  "run": [],
  "Subject2": [],
  "AnonymousSubject2": [
    "destination",
    "source"
  ],
  "BehaviorSubject2": [
    "_value"
  ],
  "ReplaySubject2": [
    "_bufferSize",
    "_windowTime",
    "_timestampProvider"
  ],
  "AsyncSubject2": [],
  "Action2": [
    "scheduler",
    "work"
  ],
  "AsyncAction2": [
    "scheduler",
    "work"
  ],
  "findAndClearHandle": [
    "handle"
  ],
  "AsapAction2": [
    "scheduler",
    "work"
  ],
  "Scheduler2": [
    "schedulerActionCtor",
    "now"
  ],
  "AsyncScheduler2": [
    "SchedulerAction",
    "now"
  ],
  "AsapScheduler2": [],
  "QueueAction2": [
    "scheduler",
    "work"
  ],
  "QueueScheduler2": [],
  "AnimationFrameAction2": [
    "scheduler",
    "work"
  ],
  "AnimationFrameScheduler2": [],
  "VirtualTimeScheduler2": [
    "schedulerActionCtor",
    "maxFrames"
  ],
  "VirtualAction2": [
    "scheduler",
    "work",
    "index"
  ],
  "empty": [
    "scheduler"
  ],
  "emptyScheduled": [
    "scheduler"
  ],
  "isScheduler": [
    "value"
  ],
  "last": [
    "arr"
  ],
  "popResultSelector": [
    "args"
  ],
  "popScheduler": [
    "args"
  ],
  "popNumber": [
    "args",
    "defaultValue"
  ],
  "isPromise": [
    "value"
  ],
  "isInteropObservable": [
    "input"
  ],
  "isAsyncIterable": [
    "obj"
  ],
  "createInvalidObservableTypeError": [
    "input"
  ],
  "getSymbolIterator": [],
  "isIterable": [
    "input"
  ],
  "verb": [
    "n"
  ],
  "step": [
    "r"
  ],
  "resume": [
    "n",
    "v"
  ],
  "fulfill": [
    "value"
  ],
  "reject": [
    "value"
  ],
  "settle": [
    "resolve",
    "reject",
    "d",
    "v"
  ],
  "readableStreamLikeToAsyncGenerator": [
    "readableStream"
  ],
  "isReadableStreamLike": [
    "obj"
  ],
  "adopt": [
    "value"
  ],
  "fulfilled": [
    "value"
  ],
  "rejected": [
    "value"
  ],
  "innerFrom": [
    "input"
  ],
  "fromInteropObservable": [
    "obj"
  ],
  "fromArrayLike": [
    "array"
  ],
  "fromPromise": [
    "promise"
  ],
  "fromIterable": [
    "iterable"
  ],
  "fromAsyncIterable": [
    "asyncIterable"
  ],
  "fromReadableStreamLike": [
    "readableStream"
  ],
  "process": [
    "asyncIterable",
    "subscriber"
  ],
  "executeSchedule": [
    "parentSubscription",
    "scheduler",
    "work",
    "delay2",
    "repeat"
  ],
  "observeOn": [
    "scheduler",
    "delay2"
  ],
  "subscribeOn": [
    "scheduler",
    "delay2"
  ],
  "scheduleObservable": [
    "input",
    "scheduler"
  ],
  "schedulePromise": [
    "input",
    "scheduler"
  ],
  "scheduleArray": [
    "input",
    "scheduler"
  ],
  "scheduleIterable": [
    "input",
    "scheduler"
  ],
  "scheduleAsyncIterable": [
    "input",
    "scheduler"
  ],
  "scheduleReadableStreamLike": [
    "input",
    "scheduler"
  ],
  "scheduled": [
    "input",
    "scheduler"
  ],
  "from": [
    "input",
    "scheduler"
  ],
  "of": [],
  "throwError": [
    "errorOrErrorFactory",
    "scheduler"
  ],
  "init": [
    "subscriber"
  ],
  "Notification2": [
    "kind",
    "value",
    "error"
  ],
  "observeNotification": [
    "notification",
    "observer"
  ],
  "isObservable": [
    "obj"
  ],
  "lastValueFrom": [
    "source",
    "config2"
  ],
  "firstValueFrom": [
    "source",
    "config2"
  ],
  "isValidDate": [
    "value"
  ],
  "startTimer": [
    "delay"
  ],
  "timeoutErrorFactory": [
    "info"
  ],
  "map": [
    "project",
    "thisArg"
  ],
  "callOrApply": [
    "fn",
    "args"
  ],
  "mapOneOrManyArgs": [
    "fn"
  ],
  "bindCallbackInternals": [
    "isNodeStyle",
    "callbackFunc",
    "resultSelector",
    "scheduler"
  ],
  "bindCallback": [
    "callbackFunc",
    "resultSelector",
    "scheduler"
  ],
  "bindNodeCallback": [
    "callbackFunc",
    "resultSelector",
    "scheduler"
  ],
  "argsArgArrayOrObject": [
    "args"
  ],
  "isPOJO": [
    "obj"
  ],
  "createObject": [
    "keys",
    "values"
  ],
  "combineLatest": [],
  "combineLatestInit": [
    "observables",
    "scheduler",
    "valueTransform"
  ],
  "_loop_1": [
    "sourceIndex2"
  ],
  "maybeSchedule": [
    "scheduler",
    "execute",
    "subscription"
  ],
  "mergeInternals": [
    "source",
    "subscriber",
    "project",
    "concurrent",
    "onBeforeNext",
    "expand",
    "innerSubScheduler",
    "additionalFinalizer"
  ],
  "checkComplete": [],
  "outerNext": [
    "value"
  ],
  "doInnerSub": [
    "value"
  ],
  "mergeMap": [
    "project",
    "resultSelector",
    "concurrent"
  ],
  "mergeAll": [
    "concurrent"
  ],
  "concatAll": [],
  "concat": [],
  "defer": [
    "observableFactory"
  ],
  "connectable": [
    "source",
    "config"
  ],
  "forkJoin": [],
  "fromEvent": [
    "target",
    "eventName",
    "options",
    "resultSelector"
  ],
  "toCommonHandlerRegistry": [
    "target",
    "eventName"
  ],
  "isNodeStyleEventEmitter": [
    "target"
  ],
  "isJQueryStyleEventEmitter": [
    "target"
  ],
  "isEventTarget": [
    "target"
  ],
  "fromEventPattern": [
    "addHandler",
    "removeHandler",
    "resultSelector"
  ],
  "generate": [
    "initialStateOrOptions",
    "condition",
    "iterate",
    "resultSelectorOrScheduler",
    "scheduler"
  ],
  "gen": [],
  "iif": [
    "condition",
    "trueResult",
    "falseResult"
  ],
  "timer": [
    "dueTime",
    "intervalOrScheduler",
    "scheduler"
  ],
  "interval": [
    "period",
    "scheduler"
  ],
  "merge": [],
  "never": [],
  "argsOrArgArray": [
    "args"
  ],
  "onErrorResumeNext": [],
  "subscribeNext": [],
  "pairs": [
    "obj",
    "scheduler"
  ],
  "not": [
    "pred",
    "thisArg"
  ],
  "filter": [
    "predicate",
    "thisArg"
  ],
  "partition": [
    "source",
    "predicate",
    "thisArg"
  ],
  "race": [],
  "raceInit": [
    "sources"
  ],
  "range": [
    "start",
    "count",
    "scheduler"
  ],
  "using": [
    "resourceFactory",
    "observableFactory"
  ],
  "zip": [],
  "audit": [
    "durationSelector"
  ],
  "endDuration": [],
  "cleanupDuration": [],
  "auditTime": [
    "duration",
    "scheduler"
  ],
  "buffer": [
    "closingNotifier"
  ],
  "bufferCount": [
    "bufferSize",
    "startBufferEvery"
  ],
  "bufferTime": [
    "bufferTimeSpan"
  ],
  "emit": [],
  "startBuffer": [],
  "bufferToggle": [
    "openings",
    "closingSelector"
  ],
  "emitBuffer": [],
  "bufferWhen": [
    "closingSelector"
  ],
  "openBuffer": [],
  "catchError": [
    "selector"
  ],
  "scanInternals": [
    "accumulator",
    "seed",
    "hasSeed",
    "emitOnNext",
    "emitBeforeComplete"
  ],
  "reduce": [
    "accumulator",
    "seed"
  ],
  "arrReducer": [
    "arr",
    "value"
  ],
  "toArray": [],
  "joinAllInternals": [
    "joinFn",
    "project"
  ],
  "combineLatestAll": [
    "project"
  ],
  "combineLatestWith": [],
  "concatMap": [
    "project",
    "resultSelector"
  ],
  "concatMapTo": [
    "innerObservable",
    "resultSelector"
  ],
  "concatWith": [],
  "fromSubscribable": [
    "subscribable"
  ],
  "connect": [
    "selector",
    "config"
  ],
  "count": [
    "predicate"
  ],
  "debounce": [
    "durationSelector"
  ],
  "debounceTime": [
    "dueTime",
    "scheduler"
  ],
  "emitWhenIdle": [],
  "defaultIfEmpty": [
    "defaultValue"
  ],
  "take": [
    "count"
  ],
  "ignoreElements": [],
  "mapTo": [
    "value"
  ],
  "delayWhen": [
    "delayDurationSelector",
    "subscriptionDelay"
  ],
  "delay": [
    "due",
    "scheduler"
  ],
  "dematerialize": [],
  "distinct": [
    "keySelector",
    "flushes"
  ],
  "distinctUntilChanged": [
    "comparator",
    "keySelector"
  ],
  "defaultCompare": [
    "a",
    "b"
  ],
  "distinctUntilKeyChanged": [
    "key",
    "compare"
  ],
  "throwIfEmpty": [
    "errorFactory"
  ],
  "defaultErrorFactory": [],
  "elementAt": [
    "index",
    "defaultValue"
  ],
  "endWith": [],
  "every": [
    "predicate",
    "thisArg"
  ],
  "exhaustMap": [
    "project",
    "resultSelector"
  ],
  "exhaustAll": [],
  "expand": [
    "project",
    "concurrent",
    "scheduler"
  ],
  "finalize": [
    "callback"
  ],
  "find": [
    "predicate",
    "thisArg"
  ],
  "createFind": [
    "predicate",
    "thisArg",
    "emit"
  ],
  "findIndex": [
    "predicate",
    "thisArg"
  ],
  "first": [
    "predicate",
    "defaultValue"
  ],
  "groupBy": [
    "keySelector",
    "elementOrOptions",
    "duration",
    "connector"
  ],
  "notify": [
    "cb"
  ],
  "createGroupedObservable": [
    "key",
    "groupSubject"
  ],
  "isEmpty": [],
  "takeLast": [
    "count"
  ],
  "materialize": [],
  "max": [
    "comparer"
  ],
  "mergeMapTo": [
    "innerObservable",
    "resultSelector",
    "concurrent"
  ],
  "mergeScan": [
    "accumulator",
    "seed",
    "concurrent"
  ],
  "mergeWith": [],
  "min": [
    "comparer"
  ],
  "multicast": [
    "subjectOrSubjectFactory",
    "selector"
  ],
  "onErrorResumeNextWith": [],
  "pairwise": [],
  "pluck": [],
  "publish": [
    "selector"
  ],
  "publishBehavior": [
    "initialValue"
  ],
  "publishLast": [],
  "publishReplay": [
    "bufferSize",
    "windowTime",
    "selectorOrScheduler",
    "timestampProvider"
  ],
  "raceWith": [],
  "repeat": [
    "countOrConfig"
  ],
  "resubscribe": [],
  "subscribeToSource": [],
  "repeatWhen": [
    "notifier"
  ],
  "getCompletionSubject": [],
  "subscribeForRepeatWhen": [],
  "retry": [
    "configOrCount"
  ],
  "subscribeForRetry": [],
  "resub_1": [],
  "retryWhen": [
    "notifier"
  ],
  "subscribeForRetryWhen": [],
  "sample": [
    "notifier"
  ],
  "sampleTime": [
    "period",
    "scheduler"
  ],
  "scan": [
    "accumulator",
    "seed"
  ],
  "sequenceEqual": [
    "compareTo",
    "comparator"
  ],
  "createSubscriber": [
    "selfState",
    "otherState"
  ],
  "createState": [],
  "share": [
    "options"
  ],
  "cancelReset": [],
  "reset": [],
  "resetAndUnsubscribe": [],
  "handleReset": [
    "reset",
    "on"
  ],
  "shareReplay": [
    "configOrBufferSize",
    "windowTime",
    "scheduler"
  ],
  "single": [
    "predicate"
  ],
  "skip": [
    "count"
  ],
  "skipLast": [
    "skipCount"
  ],
  "skipUntil": [
    "notifier"
  ],
  "skipWhile": [
    "predicate"
  ],
  "startWith": [],
  "switchMap": [
    "project",
    "resultSelector"
  ],
  "switchAll": [],
  "switchMapTo": [
    "innerObservable",
    "resultSelector"
  ],
  "switchScan": [
    "accumulator",
    "seed"
  ],
  "takeUntil": [
    "notifier"
  ],
  "takeWhile": [
    "predicate",
    "inclusive"
  ],
  "tap": [
    "observerOrNext",
    "error",
    "complete"
  ],
  "throttle": [
    "durationSelector",
    "config"
  ],
  "endThrottling": [],
  "cleanupThrottling": [],
  "startThrottle": [
    "value"
  ],
  "send": [],
  "throttleTime": [
    "duration",
    "scheduler",
    "config"
  ],
  "timeInterval": [
    "scheduler"
  ],
  "TimeInterval2": [
    "value",
    "interval"
  ],
  "timeoutWith": [
    "due",
    "withObservable",
    "scheduler"
  ],
  "timestamp": [
    "timestampProvider"
  ],
  "window": [
    "windowBoundaries"
  ],
  "errorHandler": [
    "err"
  ],
  "windowCount": [
    "windowSize",
    "startWindowEvery"
  ],
  "windowTime": [
    "windowTimeSpan"
  ],
  "closeWindow": [],
  "startWindow": [],
  "loop": [
    "cb"
  ],
  "terminate": [
    "cb"
  ],
  "windowToggle": [
    "openings",
    "closingSelector"
  ],
  "windowWhen": [
    "closingSelector"
  ],
  "openWindow": [],
  "withLatestFrom": [],
  "zipAll": [
    "project"
  ],
  "zipWith": [],
  "_checkInRHS": [
    "e"
  ],
  "_classPrivateGetter": [
    "s",
    "r",
    "a"
  ],
  "_classPrivateMethodInitSpec": [
    "e",
    "a"
  ],
  "_getRequireWildcardCache": [
    "e"
  ],
  "_interopRequireWildcard": [
    "e",
    "r"
  ],
  "_defineProperty": [
    "e",
    "r",
    "t"
  ],
  "_toPropertyKey": [
    "t"
  ],
  "_toPrimitive": [
    "t",
    "r"
  ],
  "_classPrivateFieldInitSpec": [
    "e",
    "t",
    "a"
  ],
  "_checkPrivateRedeclaration": [
    "e",
    "t"
  ],
  "_classPrivateFieldSet": [
    "s",
    "a",
    "r"
  ],
  "_classPrivateFieldGet": [
    "s",
    "a"
  ],
  "_assertClassBrand": [
    "e",
    "t",
    "n"
  ],
  "__extends": [
    "d",
    "b"
  ],
  "__awaiter": [
    "thisArg",
    "_arguments",
    "P",
    "generator"
  ],
  "__generator": [
    "thisArg",
    "body"
  ],
  "__values": [
    "o"
  ],
  "__read": [
    "o",
    "n"
  ],
  "__spreadArray": [
    "to",
    "from2",
    "pack"
  ],
  "__await": [
    "v"
  ],
  "__asyncGenerator": [
    "thisArg",
    "_arguments",
    "generator"
  ],
  "awaitReturn": [
    "f"
  ],
  "__asyncValues": [
    "o"
  ],
  "isArrayLike": [
    "x"
  ],
  "process$1": [
    "asyncIterable",
    "subscriber"
  ],
  "_finish": [
    "value"
  ],
  "rewriteError$1": [
    "error",
    "message",
    "originalMessage"
  ],
  "_update": [
    "callback"
  ],
  "_get2": [],
  "_click": [
    "options"
  ],
  "_fill": [
    "value",
    "options"
  ],
  "_hover": [
    "options"
  ],
  "_scroll": [
    "options"
  ],
  "_get_$$": [
    "_this2"
  ],
  "_$$impl": [
    "selector"
  ],
  "_checkVisibility": [
    "visibility"
  ],
  "_clickableBox": [],
  "_intersectBoundingBoxesWithFrame": [
    "boxes"
  ],
  "_getTopLeftCornerOfFrame": [],
  "_nonEmptyVisibleBoundingBox": [],
  "_asSVGElementHandle": [],
  "_getOwnerSVGElement": [],
  "_document2": [],
  "_getNativePixelDimensions": [],
  "_isPlainTextField": [],
  "_isTextOnlyObject": [],
  "_hasFocusableChild": [],
  "_onClose": [],
  "_onExecutionContextsCleared": [],
  "_onScriptParsed": [
    "event"
  ],
  "_onExecutionContextsCleared2": [],
  "_onStyleSheet": [
    "event"
  ],
  "_get_applyViewport": [
    "_this3"
  ],
  "_get_emulateIdleState": [
    "_this4"
  ],
  "_get_emulateTimezone": [
    "_this5"
  ],
  "_get_emulateVisionDeficiency": [
    "_this6"
  ],
  "_get_emulateCpuThrottling": [
    "_this7"
  ],
  "_get_emulateMediaFeatures": [
    "_this8"
  ],
  "_get_emulateMediaType": [
    "_this9"
  ],
  "_get_setGeolocation": [
    "_this10"
  ],
  "_get_setDefaultBackgroundColor": [
    "_this11"
  ],
  "_get_setJavaScriptEnabled": [
    "_this12"
  ],
  "_get_emulateFocus": [
    "_this13"
  ],
  "_updateDevices": [
    "event"
  ],
  "_onDeviceRequestPrompted": [
    "event"
  ],
  "_get_frameManager": [
    "_this14"
  ],
  "_addBinding": [
    "binding"
  ],
  "_onBindingCalled": [
    "event"
  ],
  "_onConsoleAPI": [
    "event"
  ],
  "_addBindingWithoutThrowing": [
    "binding"
  ],
  "_evaluate": [
    "returnByValue",
    "pageFunction",
    "param"
  ],
  "_onContextDisposed": [],
  "_onContextConsoleApiCalled": [
    "event"
  ],
  "_onContextBindingCalled": [
    "event"
  ],
  "_executionContext": [],
  "_waitForExecutionContext": [],
  "_onRequest": [
    "request"
  ],
  "_onRequestFailed": [
    "request"
  ],
  "_onResponse": [
    "response"
  ],
  "_onFrameDetached": [
    "frame"
  ],
  "_navigatedWithinDocument": [],
  "_navigated": [
    "navigationType"
  ],
  "_frameSwapped": [],
  "_checkLifecycleComplete": [],
  "_onMainWorldConsoleApiCalled": [
    "event"
  ],
  "_onMainWorldBindingCalled": [
    "event"
  ],
  "_deviceRequestPromptManager": [],
  "_parseStatusTextFromExtraInfo": [
    "extraInfo"
  ],
  "_canIgnoreError": [
    "error"
  ],
  "_removeClient": [
    "client"
  ],
  "_applyExtraHTTPHeaders": [
    "client"
  ],
  "_applyToAllClients": [
    "fn"
  ],
  "_applyNetworkConditions": [
    "client"
  ],
  "_applyUserAgent": [
    "client"
  ],
  "_applyProtocolRequestInterception": [
    "client"
  ],
  "_applyProtocolCacheDisabled": [
    "client"
  ],
  "_onRequestWillBeSent": [
    "client",
    "event"
  ],
  "_onAuthRequired": [
    "client",
    "event"
  ],
  "_onRequestPaused": [
    "client",
    "event"
  ],
  "_patchRequestEventHeaders": [
    "requestWillBeSentEvent",
    "requestPausedEvent"
  ],
  "_onRequestWithoutNetworkInstrumentation": [
    "client",
    "event"
  ],
  "_onRequest2": [
    "client",
    "event",
    "fetchRequestId",
    "param"
  ],
  "_onRequestWillBeSentExtraInfo": [
    "_client",
    "event"
  ],
  "_onRequestServedFromCache": [
    "client",
    "event"
  ],
  "_handleRequestRedirect": [
    "_client",
    "request",
    "responsePayload",
    "extraInfo"
  ],
  "_emitResponseEvent": [
    "_client",
    "responseReceived",
    "extraInfo"
  ],
  "_onResponseReceived": [
    "client",
    "event"
  ],
  "_onResponseReceivedExtraInfo": [
    "client",
    "event"
  ],
  "_forgetRequest": [
    "request",
    "events"
  ],
  "_onLoadingFinished": [
    "client",
    "event"
  ],
  "_emitLoadingFinished": [
    "client",
    "event"
  ],
  "_onLoadingFailed": [
    "client",
    "event"
  ],
  "_emitLoadingFailed": [
    "client",
    "event"
  ],
  "_adoptCdpSessionIfNeeded": [
    "client",
    "request"
  ],
  "_onClientDisconnect": [],
  "_onLifecycleEvent": [
    "event"
  ],
  "_onFrameStartedLoading": [
    "frameId"
  ],
  "_onFrameStoppedLoading": [
    "frameId"
  ],
  "_handleFrameTree": [
    "session",
    "frameTree"
  ],
  "_onFrameAttached": [
    "session",
    "frameId",
    "parentFrameId"
  ],
  "_onFrameNavigated": [
    "framePayload",
    "navigationType"
  ],
  "_createIsolatedWorld": [
    "session",
    "name"
  ],
  "_onFrameNavigatedWithinDocument": [
    "frameId",
    "url"
  ],
  "_onFrameDetached2": [
    "frameId",
    "reason"
  ],
  "_onExecutionContextCreated": [
    "contextPayload",
    "session"
  ],
  "_removeFramesRecursively": [
    "frame"
  ],
  "_modifierBit": [
    "key"
  ],
  "_keyDescriptionForString": [
    "keyString"
  ],
  "_get_state": [
    "_this15"
  ],
  "_createTransaction": [],
  "_withTransaction": [
    "action"
  ],
  "_attachExistingTargets": [],
  "_onActivation": [
    "newSession"
  ],
  "_onSecondaryTarget": [
    "session"
  ],
  "_setupPrimaryTargetListeners": [],
  "_initialize": [],
  "_onFileChooser": [
    "event"
  ],
  "_onTargetCrashed": [],
  "_onLogEntryAdded": [
    "event"
  ],
  "_emitMetrics": [
    "event"
  ],
  "_buildMetricsObject": [
    "metrics"
  ],
  "_handleException": [
    "exception"
  ],
  "_onConsoleAPI2": [
    "world",
    "event"
  ],
  "_onBindingCalled2": [
    "world",
    "event"
  ],
  "_onDialog": [
    "event"
  ],
  "_go": [
    "delta",
    "options"
  ],
  "_setupAttachmentListeners": [
    "session"
  ],
  "_removeAttachmentListeners": [
    "session"
  ],
  "_finishInitializationIfReady": [
    "targetId"
  ],
  "_setIsPageTargetCallback": [
    "isPageTargetCallback"
  ],
  "_getVersion": [],
  "_dispatchResponse": [
    "message"
  ]
}