{
  "clamp": [
    "v",
    "minimum",
    "max"
  ],
  "configureProperties": [
    "obj"
  ],
  "makeArrayAccessors": [
    "obj"
  ],
  "makeArrayAccessor": [
    "index"
  ],
  "as_signed": [
    "value",
    "bits"
  ],
  "as_unsigned": [
    "value",
    "bits"
  ],
  "packI8": [
    "n"
  ],
  "unpackI8": [
    "bytes"
  ],
  "packU8": [
    "n"
  ],
  "unpackU8": [
    "bytes"
  ],
  "packU8Clamped": [
    "n"
  ],
  "packI16": [
    "n"
  ],
  "unpackI16": [
    "bytes"
  ],
  "packU16": [
    "n"
  ],
  "unpackU16": [
    "bytes"
  ],
  "packI32": [
    "n"
  ],
  "unpackI32": [
    "bytes"
  ],
  "packU32": [
    "n"
  ],
  "unpackU32": [
    "bytes"
  ],
  "packIEEE754": [
    "v",
    "ebits",
    "fbits"
  ],
  "roundToEven": [
    "n"
  ],
  "unpackIEEE754": [
    "bytes",
    "ebits",
    "fbits"
  ],
  "unpackF64": [
    "b"
  ],
  "packF64": [
    "v"
  ],
  "unpackF32": [
    "b"
  ],
  "packF32": [
    "v"
  ],
  "ArrayBuffer": [
    "length"
  ],
  "ArrayBufferView": [],
  "makeConstructor": [
    "bytesPerElement",
    "pack",
    "unpack"
  ],
  "r": [
    "array",
    "index"
  ],
  "DataView": [
    "buffer",
    "byteOffset",
    "byteLength"
  ],
  "makeGetter": [
    "arrayType"
  ],
  "makeSetter": [
    "arrayType"
  ]
}