{
  "CacheFirst": {
    "_handle": [
      "request",
      "handler"
    ]
  },
  "CacheOnly": {
    "_handle": [
      "request",
      "handler"
    ]
  },
  "NetworkFirst": {
    "_networkTimeoutSeconds": [],
    "constructor": [
      "param"
    ],
    "_handle": [
      "request",
      "handler"
    ],
    "_getTimeoutPromise": [
      "param"
    ],
    "_getNetworkPromise": [
      "param"
    ]
  },
  "onNetworkTimeout": [],
  "NetworkOnly": {
    "_networkTimeoutSeconds": [],
    "constructor": [
      "param"
    ],
    "_handle": [
      "request",
      "handler"
    ]
  },
  "StaleWhileRevalidate": {
    "constructor": [
      "param"
    ],
    "_handle": [
      "request",
      "handler"
    ]
  },
  "Strategy": {
    "cacheName": [],
    "plugins": [],
    "fetchOptions": [],
    "matchOptions": [],
    "_handle": [
      "request",
      "handler"
    ],
    "constructor": [
      "param"
    ],
    "handle": [
      "options"
    ],
    "handleAll": [
      "options"
    ],
    "_getResponse": [
      "handler",
      "request",
      "event"
    ],
    "_awaitComplete": [
      "responseDone",
      "handler",
      "request",
      "event"
    ]
  },
  "StrategyHandler": {
    "request": [],
    "url": [],
    "event": [],
    "params": [],
    "_cacheKeys": [],
    "_strategy": [],
    "_extendLifetimePromises": [],
    "_handlerDeferred": [],
    "_plugins": [],
    "_pluginStateMap": [],
    "constructor": [
      "strategy",
      "options"
    ],
    "fetch": [
      "input"
    ],
    "fetchAndCachePut": [
      "input"
    ],
    "cacheMatch": [
      "key"
    ],
    "cachePut": [
      "key",
      "response"
    ],
    "getCacheKey": [
      "request",
      "mode"
    ],
    "hasCallback": [
      "name"
    ],
    "runCallbacks": [
      "name",
      "param"
    ],
    "iterateCallbacks": [
      "name"
    ],
    "waitUntil": [
      "promise"
    ],
    "doneWaiting": [],
    "destroy": [],
    "_ensureResponseSafeToCache": [
      "response"
    ]
  },
  "toRequest": [
    "input"
  ],
  "statefulCallback": [
    "param"
  ],
  "h": [
    "t"
  ],
  "l": {
    "constructor": [
      "t",
      "e"
    ],
    "fetch": [
      "t"
    ],
    "fetchAndCachePut": [
      "t"
    ],
    "cacheMatch": [
      "t"
    ],
    "cachePut": [
      "t",
      "s"
    ],
    "getCacheKey": [
      "t",
      "e"
    ],
    "hasCallback": [
      "t"
    ],
    "runCallbacks": [
      "t",
      "e"
    ],
    "iterateCallbacks": [
      "t"
    ],
    "waitUntil": [
      "t"
    ],
    "doneWaiting": [],
    "destroy": [],
    "g": [
      "t"
    ]
  },
  "r": [
    "r"
  ],
  "w": {
    "constructor": [
      "param"
    ],
    "handle": [
      "t"
    ],
    "handleAll": [
      "t"
    ],
    "_": [
      "t",
      "s",
      "r"
    ],
    "k": [
      "t",
      "e",
      "s",
      "r"
    ]
  }
}